[
  {
    "broadcast": true,
    "messageType": "BROADCAST_TEAMS",
    "data": [
      {
        "name": "Team 1",
        "players": [
          {
            "name": "roman",
            "id": "93b80902-df6b-4f25-9c4e-590282b6c91f",
            "seatId": 0
          },
          {
            "name": "nadja",
            "id": "613d12df-a58a-4539-bd8f-88eae4ff377e",
            "seatId": 2
          }
        ]
      },
      {
        "name": "Team 2",
        "players": [
          {
            "name": "bello",
            "id": "800517c2-ee60-4447-8c39-10f7fdf828e7",
            "seatId": 1
          },
          {
            "name": "bella",
            "id": "5d06ca0b-a6c2-48d3-8896-893a4007cc24",
            "seatId": 3
          }
        ]
      }
    ]
  },
  {
    "broadcast": false,
    "sentTo": "roman#0",
    "messageType": "DEAL_CARDS",
    "data": [
      {
        "number": 6,
        "color": "CLUBS"
      },
      {
        "number": 7,
        "color": "CLUBS"
      },
      {
        "number": 8,
        "color": "CLUBS"
      },
      {
        "number": 9,
        "color": "CLUBS"
      },
      {
        "number": 10,
        "color": "CLUBS"
      },
      {
        "number": 11,
        "color": "CLUBS"
      },
      {
        "number": 12,
        "color": "CLUBS"
      },
      {
        "number": 13,
        "color": "CLUBS"
      },
      {
        "number": 14,
        "color": "CLUBS"
      }
    ]
  },
  {
    "broadcast": false,
    "sentTo": "bello#1",
    "messageType": "DEAL_CARDS",
    "data": [
      {
        "number": 8,
        "color": "DIAMONDS"
      },
      {
        "number": 8,
        "color": "HEARTS"
      },
      {
        "number": 8,
        "color": "SPADES"
      },
      {
        "number": 6,
        "color": "SPADES"
      },
      {
        "number": 9,
        "color": "DIAMONDS"
      },
      {
        "number": 9,
        "color": "HEARTS"
      },
      {
        "number": 9,
        "color": "SPADES"
      },
      {
        "number": 6,
        "color": "DIAMONDS"
      },
      {
        "number": 10,
        "color": "DIAMONDS"
      }
    ]
  },
  {
    "broadcast": false,
    "sentTo": "nadja#2",
    "messageType": "DEAL_CARDS",
    "data": [
      {
        "number": 10,
        "color": "HEARTS"
      },
      {
        "number": 10,
        "color": "SPADES"
      },
      {
        "number": 7,
        "color": "DIAMONDS"
      },
      {
        "number": 11,
        "color": "DIAMONDS"
      },
      {
        "number": 11,
        "color": "HEARTS"
      },
      {
        "number": 11,
        "color": "SPADES"
      },
      {
        "number": 7,
        "color": "HEARTS"
      },
      {
        "number": 12,
        "color": "DIAMONDS"
      },
      {
        "number": 12,
        "color": "HEARTS"
      }
    ]
  },
  {
    "broadcast": false,
    "sentTo": "bella#3",
    "messageType": "DEAL_CARDS",
    "data": [
      {
        "number": 12,
        "color": "SPADES"
      },
      {
        "number": 7,
        "color": "SPADES"
      },
      {
        "number": 13,
        "color": "DIAMONDS"
      },
      {
        "number": 13,
        "color": "HEARTS"
      },
      {
        "number": 13,
        "color": "SPADES"
      },
      {
        "number": 6,
        "color": "HEARTS"
      },
      {
        "number": 14,
        "color": "DIAMONDS"
      },
      {
        "number": 14,
        "color": "HEARTS"
      },
      {
        "number": 14,
        "color": "SPADES"
      }
    ]
  },
  {
    "broadcast": false,
    "sentTo": "roman#0",
    "messageType": "REQUEST_TRUMPF",
    "data": false
  },
  {
    "broadcast": false,
    "receivedFrom": "roman#0",
    "messageType": "CHOOSE_TRUMPF",
    "data": {
      "mode": "TRUMPF",
      "trumpfColor": "CLUBS"
    }
  },
  {
    "broadcast": true,
    "messageType": "BROADCAST_TRUMPF",
    "data": {
      "mode": "TRUMPF",
      "trumpfColor": "CLUBS"
    }
  },
  {
    "broadcast": false,
    "sentTo": "roman#0",
    "messageType": "REQUEST_CARD",
    "data": []
  },
  {
    "broadcast": false,
    "receivedFrom": "roman#0",
    "messageType": "CHOOSE_CARD",
    "data": {
      "number": 11,
      "color": "CLUBS"
    }
  },
  {
    "broadcast": true,
    "messageType": "PLAYED_CARDS",
    "data": [
      {
        "number": 11,
        "color": "CLUBS"
      }
    ]
  },
  {
    "broadcast": false,
    "sentTo": "bello#1",
    "messageType": "REQUEST_CARD",
    "data": [
      {
        "number": 11,
        "color": "CLUBS"
      }
    ]
  },
  {
    "broadcast": false,
    "receivedFrom": "bello#1",
    "messageType": "CHOOSE_CARD",
    "data": {
      "number": 10,
      "color": "DIAMONDS"
    }
  },
  {
    "broadcast": true,
    "messageType": "PLAYED_CARDS",
    "data": [
      {
        "number": 11,
        "color": "CLUBS"
      },
      {
        "number": 10,
        "color": "DIAMONDS"
      }
    ]
  },
  {
    "broadcast": false,
    "sentTo": "nadja#2",
    "messageType": "REQUEST_CARD",
    "data": [
      {
        "number": 11,
        "color": "CLUBS"
      },
      {
        "number": 10,
        "color": "DIAMONDS"
      }
    ]
  },
  {
    "broadcast": false,
    "receivedFrom": "nadja#2",
    "messageType": "CHOOSE_CARD",
    "data": {
      "number": 11,
      "color": "DIAMONDS"
    }
  },
  {
    "broadcast": true,
    "messageType": "PLAYED_CARDS",
    "data": [
      {
        "number": 11,
        "color": "CLUBS"
      },
      {
        "number": 10,
        "color": "DIAMONDS"
      },
      {
        "number": 11,
        "color": "DIAMONDS"
      }
    ]
  },
  {
    "broadcast": false,
    "sentTo": "bella#3",
    "messageType": "REQUEST_CARD",
    "data": [
      {
        "number": 11,
        "color": "CLUBS"
      },
      {
        "number": 10,
        "color": "DIAMONDS"
      },
      {
        "number": 11,
        "color": "DIAMONDS"
      }
    ]
  },
  {
    "broadcast": false,
    "receivedFrom": "bella#3",
    "messageType": "CHOOSE_CARD",
    "data": {
      "number": 7,
      "color": "SPADES"
    }
  },
  {
    "broadcast": true,
    "messageType": "PLAYED_CARDS",
    "data": [
      {
        "number": 11,
        "color": "CLUBS"
      },
      {
        "number": 10,
        "color": "DIAMONDS"
      },
      {
        "number": 11,
        "color": "DIAMONDS"
      },
      {
        "number": 7,
        "color": "SPADES"
      }
    ]
  },
  {
    "broadcast": true,
    "messageType": "BROADCAST_STICH",
    "data": {
      "name": "roman",
      "id": "93b80902-df6b-4f25-9c4e-590282b6c91f",
      "seatId": 0,
      "playedCards": [
        {
          "number": 11,
          "color": "CLUBS"
        },
        {
          "number": 10,
          "color": "DIAMONDS"
        },
        {
          "number": 11,
          "color": "DIAMONDS"
        },
        {
          "number": 7,
          "color": "SPADES"
        }
      ],
      "teams": [
        {
          "name": "Team 1",
          "points": 64,
          "currentRoundPoints": 64
        },
        {
          "name": "Team 2",
          "points": 0,
          "currentRoundPoints": 0
        }
      ]
    }
  },
  {
    "broadcast": false,
    "sentTo": "roman#0",
    "messageType": "REQUEST_CARD",
    "data": []
  },
  {
    "broadcast": false,
    "receivedFrom": "roman#0",
    "messageType": "CHOOSE_CARD",
    "data": {
      "number": 10,
      "color": "CLUBS"
    }
  },
  {
    "broadcast": true,
    "messageType": "PLAYED_CARDS",
    "data": [
      {
        "number": 10,
        "color": "CLUBS"
      }
    ]
  },
  {
    "broadcast": false,
    "sentTo": "bello#1",
    "messageType": "REQUEST_CARD",
    "data": [
      {
        "number": 10,
        "color": "CLUBS"
      }
    ]
  },
  {
    "broadcast": false,
    "receivedFrom": "bello#1",
    "messageType": "CHOOSE_CARD",
    "data": {
      "number": 9,
      "color": "DIAMONDS"
    }
  },
  {
    "broadcast": true,
    "messageType": "PLAYED_CARDS",
    "data": [
      {
        "number": 10,
        "color": "CLUBS"
      },
      {
        "number": 9,
        "color": "DIAMONDS"
      }
    ]
  },
  {
    "broadcast": false,
    "sentTo": "nadja#2",
    "messageType": "REQUEST_CARD",
    "data": [
      {
        "number": 10,
        "color": "CLUBS"
      },
      {
        "number": 9,
        "color": "DIAMONDS"
      }
    ]
  },
  {
    "broadcast": false,
    "receivedFrom": "nadja#2",
    "messageType": "CHOOSE_CARD",
    "data": {
      "number": 7,
      "color": "DIAMONDS"
    }
  },
  {
    "broadcast": true,
    "messageType": "PLAYED_CARDS",
    "data": [
      {
        "number": 10,
        "color": "CLUBS"
      },
      {
        "number": 9,
        "color": "DIAMONDS"
      },
      {
        "number": 7,
        "color": "DIAMONDS"
      }
    ]
  },
  {
    "broadcast": false,
    "sentTo": "bella#3",
    "messageType": "REQUEST_CARD",
    "data": [
      {
        "number": 10,
        "color": "CLUBS"
      },
      {
        "number": 9,
        "color": "DIAMONDS"
      },
      {
        "number": 7,
        "color": "DIAMONDS"
      }
    ]
  },
  {
    "broadcast": false,
    "receivedFrom": "bella#3",
    "messageType": "CHOOSE_CARD",
    "data": {
      "number": 14,
      "color": "DIAMONDS"
    }
  },
  {
    "broadcast": true,
    "messageType": "PLAYED_CARDS",
    "data": [
      {
        "number": 10,
        "color": "CLUBS"
      },
      {
        "number": 9,
        "color": "DIAMONDS"
      },
      {
        "number": 7,
        "color": "DIAMONDS"
      },
      {
        "number": 14,
        "color": "DIAMONDS"
      }
    ]
  },
  {
    "broadcast": true,
    "messageType": "BROADCAST_STICH",
    "data": {
      "name": "roman",
      "id": "93b80902-df6b-4f25-9c4e-590282b6c91f",
      "seatId": 0,
      "playedCards": [
        {
          "number": 10,
          "color": "CLUBS"
        },
        {
          "number": 9,
          "color": "DIAMONDS"
        },
        {
          "number": 7,
          "color": "DIAMONDS"
        },
        {
          "number": 14,
          "color": "DIAMONDS"
        }
      ],
      "teams": [
        {
          "name": "Team 1",
          "points": 106,
          "currentRoundPoints": 106
        },
        {
          "name": "Team 2",
          "points": 0,
          "currentRoundPoints": 0
        }
      ]
    }
  },
  {
    "broadcast": false,
    "sentTo": "roman#0",
    "messageType": "REQUEST_CARD",
    "data": []
  },
  {
    "broadcast": false,
    "receivedFrom": "roman#0",
    "messageType": "CHOOSE_CARD",
    "data": {
      "number": 12,
      "color": "CLUBS"
    }
  },
  {
    "broadcast": true,
    "messageType": "PLAYED_CARDS",
    "data": [
      {
        "number": 12,
        "color": "CLUBS"
      }
    ]
  },
  {
    "broadcast": false,
    "sentTo": "bello#1",
    "messageType": "REQUEST_CARD",
    "data": [
      {
        "number": 12,
        "color": "CLUBS"
      }
    ]
  },
  {
    "broadcast": false,
    "receivedFrom": "bello#1",
    "messageType": "CHOOSE_CARD",
    "data": {
      "number": 6,
      "color": "SPADES"
    }
  },
  {
    "broadcast": true,
    "messageType": "PLAYED_CARDS",
    "data": [
      {
        "number": 12,
        "color": "CLUBS"
      },
      {
        "number": 6,
        "color": "SPADES"
      }
    ]
  },
  {
    "broadcast": false,
    "sentTo": "nadja#2",
    "messageType": "REQUEST_CARD",
    "data": [
      {
        "number": 12,
        "color": "CLUBS"
      },
      {
        "number": 6,
        "color": "SPADES"
      }
    ]
  },
  {
    "broadcast": false,
    "receivedFrom": "nadja#2",
    "messageType": "CHOOSE_CARD",
    "data": {
      "number": 12,
      "color": "DIAMONDS"
    }
  },
  {
    "broadcast": true,
    "messageType": "PLAYED_CARDS",
    "data": [
      {
        "number": 12,
        "color": "CLUBS"
      },
      {
        "number": 6,
        "color": "SPADES"
      },
      {
        "number": 12,
        "color": "DIAMONDS"
      }
    ]
  },
  {
    "broadcast": false,
    "sentTo": "bella#3",
    "messageType": "REQUEST_CARD",
    "data": [
      {
        "number": 12,
        "color": "CLUBS"
      },
      {
        "number": 6,
        "color": "SPADES"
      },
      {
        "number": 12,
        "color": "DIAMONDS"
      }
    ]
  },
  {
    "broadcast": false,
    "receivedFrom": "bella#3",
    "messageType": "CHOOSE_CARD",
    "data": {
      "number": 12,
      "color": "SPADES"
    }
  },
  {
    "broadcast": true,
    "messageType": "PLAYED_CARDS",
    "data": [
      {
        "number": 12,
        "color": "CLUBS"
      },
      {
        "number": 6,
        "color": "SPADES"
      },
      {
        "number": 12,
        "color": "DIAMONDS"
      },
      {
        "number": 12,
        "color": "SPADES"
      }
    ]
  },
  {
    "broadcast": true,
    "messageType": "BROADCAST_STICH",
    "data": {
      "name": "roman",
      "id": "93b80902-df6b-4f25-9c4e-590282b6c91f",
      "seatId": 0,
      "playedCards": [
        {
          "number": 12,
          "color": "CLUBS"
        },
        {
          "number": 6,
          "color": "SPADES"
        },
        {
          "number": 12,
          "color": "DIAMONDS"
        },
        {
          "number": 12,
          "color": "SPADES"
        }
      ],
      "teams": [
        {
          "name": "Team 1",
          "points": 124,
          "currentRoundPoints": 124
        },
        {
          "name": "Team 2",
          "points": 0,
          "currentRoundPoints": 0
        }
      ]
    }
  },
  {
    "broadcast": false,
    "sentTo": "roman#0",
    "messageType": "REQUEST_CARD",
    "data": []
  },
  {
    "broadcast": false,
    "receivedFrom": "roman#0",
    "messageType": "CHOOSE_CARD",
    "data": {
      "number": 9,
      "color": "CLUBS"
    }
  },
  {
    "broadcast": true,
    "messageType": "PLAYED_CARDS",
    "data": [
      {
        "number": 9,
        "color": "CLUBS"
      }
    ]
  },
  {
    "broadcast": false,
    "sentTo": "bello#1",
    "messageType": "REQUEST_CARD",
    "data": [
      {
        "number": 9,
        "color": "CLUBS"
      }
    ]
  },
  {
    "broadcast": false,
    "receivedFrom": "bello#1",
    "messageType": "CHOOSE_CARD",
    "data": {
      "number": 8,
      "color": "DIAMONDS"
    }
  },
  {
    "broadcast": true,
    "messageType": "PLAYED_CARDS",
    "data": [
      {
        "number": 9,
        "color": "CLUBS"
      },
      {
        "number": 8,
        "color": "DIAMONDS"
      }
    ]
  },
  {
    "broadcast": false,
    "sentTo": "nadja#2",
    "messageType": "REQUEST_CARD",
    "data": [
      {
        "number": 9,
        "color": "CLUBS"
      },
      {
        "number": 8,
        "color": "DIAMONDS"
      }
    ]
  },
  {
    "broadcast": false,
    "receivedFrom": "nadja#2",
    "messageType": "CHOOSE_CARD",
    "data": {
      "number": 12,
      "color": "HEARTS"
    }
  },
  {
    "broadcast": true,
    "messageType": "PLAYED_CARDS",
    "data": [
      {
        "number": 9,
        "color": "CLUBS"
      },
      {
        "number": 8,
        "color": "DIAMONDS"
      },
      {
        "number": 12,
        "color": "HEARTS"
      }
    ]
  },
  {
    "broadcast": false,
    "sentTo": "bella#3",
    "messageType": "REQUEST_CARD",
    "data": [
      {
        "number": 9,
        "color": "CLUBS"
      },
      {
        "number": 8,
        "color": "DIAMONDS"
      },
      {
        "number": 12,
        "color": "HEARTS"
      }
    ]
  },
  {
    "broadcast": false,
    "receivedFrom": "bella#3",
    "messageType": "CHOOSE_CARD",
    "data": {
      "number": 13,
      "color": "DIAMONDS"
    }
  },
  {
    "broadcast": true,
    "messageType": "PLAYED_CARDS",
    "data": [
      {
        "number": 9,
        "color": "CLUBS"
      },
      {
        "number": 8,
        "color": "DIAMONDS"
      },
      {
        "number": 12,
        "color": "HEARTS"
      },
      {
        "number": 13,
        "color": "DIAMONDS"
      }
    ]
  },
  {
    "broadcast": true,
    "messageType": "BROADCAST_STICH",
    "data": {
      "name": "roman",
      "id": "93b80902-df6b-4f25-9c4e-590282b6c91f",
      "seatId": 0,
      "playedCards": [
        {
          "number": 9,
          "color": "CLUBS"
        },
        {
          "number": 8,
          "color": "DIAMONDS"
        },
        {
          "number": 12,
          "color": "HEARTS"
        },
        {
          "number": 13,
          "color": "DIAMONDS"
        }
      ],
      "teams": [
        {
          "name": "Team 1",
          "points": 166,
          "currentRoundPoints": 166
        },
        {
          "name": "Team 2",
          "points": 0,
          "currentRoundPoints": 0
        }
      ]
    }
  },
  {
    "broadcast": false,
    "sentTo": "roman#0",
    "messageType": "REQUEST_CARD",
    "data": []
  },
  {
    "broadcast": false,
    "receivedFrom": "roman#0",
    "messageType": "CHOOSE_CARD",
    "data": {
      "number": 13,
      "color": "CLUBS"
    }
  },
  {
    "broadcast": true,
    "messageType": "PLAYED_CARDS",
    "data": [
      {
        "number": 13,
        "color": "CLUBS"
      }
    ]
  },
  {
    "broadcast": false,
    "sentTo": "bello#1",
    "messageType": "REQUEST_CARD",
    "data": [
      {
        "number": 13,
        "color": "CLUBS"
      }
    ]
  },
  {
    "broadcast": false,
    "receivedFrom": "bello#1",
    "messageType": "CHOOSE_CARD",
    "data": {
      "number": 8,
      "color": "SPADES"
    }
  },
  {
    "broadcast": true,
    "messageType": "PLAYED_CARDS",
    "data": [
      {
        "number": 13,
        "color": "CLUBS"
      },
      {
        "number": 8,
        "color": "SPADES"
      }
    ]
  },
  {
    "broadcast": false,
    "sentTo": "nadja#2",
    "messageType": "REQUEST_CARD",
    "data": [
      {
        "number": 13,
        "color": "CLUBS"
      },
      {
        "number": 8,
        "color": "SPADES"
      }
    ]
  },
  {
    "broadcast": false,
    "receivedFrom": "nadja#2",
    "messageType": "CHOOSE_CARD",
    "data": {
      "number": 10,
      "color": "SPADES"
    }
  },
  {
    "broadcast": true,
    "messageType": "PLAYED_CARDS",
    "data": [
      {
        "number": 13,
        "color": "CLUBS"
      },
      {
        "number": 8,
        "color": "SPADES"
      },
      {
        "number": 10,
        "color": "SPADES"
      }
    ]
  },
  {
    "broadcast": false,
    "sentTo": "bella#3",
    "messageType": "REQUEST_CARD",
    "data": [
      {
        "number": 13,
        "color": "CLUBS"
      },
      {
        "number": 8,
        "color": "SPADES"
      },
      {
        "number": 10,
        "color": "SPADES"
      }
    ]
  },
  {
    "broadcast": false,
    "receivedFrom": "bella#3",
    "messageType": "CHOOSE_CARD",
    "data": {
      "number": 13,
      "color": "SPADES"
    }
  },
  {
    "broadcast": true,
    "messageType": "PLAYED_CARDS",
    "data": [
      {
        "number": 13,
        "color": "CLUBS"
      },
      {
        "number": 8,
        "color": "SPADES"
      },
      {
        "number": 10,
        "color": "SPADES"
      },
      {
        "number": 13,
        "color": "SPADES"
      }
    ]
  },
  {
    "broadcast": true,
    "messageType": "BROADCAST_STICH",
    "data": {
      "name": "roman",
      "id": "93b80902-df6b-4f25-9c4e-590282b6c91f",
      "seatId": 0,
      "playedCards": [
        {
          "number": 13,
          "color": "CLUBS"
        },
        {
          "number": 8,
          "color": "SPADES"
        },
        {
          "number": 10,
          "color": "SPADES"
        },
        {
          "number": 13,
          "color": "SPADES"
        }
      ],
      "teams": [
        {
          "name": "Team 1",
          "points": 202,
          "currentRoundPoints": 202
        },
        {
          "name": "Team 2",
          "points": 0,
          "currentRoundPoints": 0
        }
      ]
    }
  },
  {
    "broadcast": false,
    "sentTo": "roman#0",
    "messageType": "REQUEST_CARD",
    "data": []
  },
  {
    "broadcast": false,
    "receivedFrom": "roman#0",
    "messageType": "CHOOSE_CARD",
    "data": {
      "number": 8,
      "color": "CLUBS"
    }
  },
  {
    "broadcast": true,
    "messageType": "PLAYED_CARDS",
    "data": [
      {
        "number": 8,
        "color": "CLUBS"
      }
    ]
  },
  {
    "broadcast": false,
    "sentTo": "bello#1",
    "messageType": "REQUEST_CARD",
    "data": [
      {
        "number": 8,
        "color": "CLUBS"
      }
    ]
  },
  {
    "broadcast": false,
    "receivedFrom": "bello#1",
    "messageType": "CHOOSE_CARD",
    "data": {
      "number": 6,
      "color": "DIAMONDS"
    }
  },
  {
    "broadcast": true,
    "messageType": "PLAYED_CARDS",
    "data": [
      {
        "number": 8,
        "color": "CLUBS"
      },
      {
        "number": 6,
        "color": "DIAMONDS"
      }
    ]
  },
  {
    "broadcast": false,
    "sentTo": "nadja#2",
    "messageType": "REQUEST_CARD",
    "data": [
      {
        "number": 8,
        "color": "CLUBS"
      },
      {
        "number": 6,
        "color": "DIAMONDS"
      }
    ]
  },
  {
    "broadcast": false,
    "receivedFrom": "nadja#2",
    "messageType": "CHOOSE_CARD",
    "data": {
      "number": 11,
      "color": "HEARTS"
    }
  },
  {
    "broadcast": true,
    "messageType": "PLAYED_CARDS",
    "data": [
      {
        "number": 8,
        "color": "CLUBS"
      },
      {
        "number": 6,
        "color": "DIAMONDS"
      },
      {
        "number": 11,
        "color": "HEARTS"
      }
    ]
  },
  {
    "broadcast": false,
    "sentTo": "bella#3",
    "messageType": "REQUEST_CARD",
    "data": [
      {
        "number": 8,
        "color": "CLUBS"
      },
      {
        "number": 6,
        "color": "DIAMONDS"
      },
      {
        "number": 11,
        "color": "HEARTS"
      }
    ]
  },
  {
    "broadcast": false,
    "receivedFrom": "bella#3",
    "messageType": "CHOOSE_CARD",
    "data": {
      "number": 14,
      "color": "HEARTS"
    }
  },
  {
    "broadcast": true,
    "messageType": "PLAYED_CARDS",
    "data": [
      {
        "number": 8,
        "color": "CLUBS"
      },
      {
        "number": 6,
        "color": "DIAMONDS"
      },
      {
        "number": 11,
        "color": "HEARTS"
      },
      {
        "number": 14,
        "color": "HEARTS"
      }
    ]
  },
  {
    "broadcast": true,
    "messageType": "BROADCAST_STICH",
    "data": {
      "name": "roman",
      "id": "93b80902-df6b-4f25-9c4e-590282b6c91f",
      "seatId": 0,
      "playedCards": [
        {
          "number": 8,
          "color": "CLUBS"
        },
        {
          "number": 6,
          "color": "DIAMONDS"
        },
        {
          "number": 11,
          "color": "HEARTS"
        },
        {
          "number": 14,
          "color": "HEARTS"
        }
      ],
      "teams": [
        {
          "name": "Team 1",
          "points": 228,
          "currentRoundPoints": 228
        },
        {
          "name": "Team 2",
          "points": 0,
          "currentRoundPoints": 0
        }
      ]
    }
  },
  {
    "broadcast": false,
    "sentTo": "roman#0",
    "messageType": "REQUEST_CARD",
    "data": []
  },
  {
    "broadcast": false,
    "receivedFrom": "roman#0",
    "messageType": "CHOOSE_CARD",
    "data": {
      "number": 14,
      "color": "CLUBS"
    }
  },
  {
    "broadcast": true,
    "messageType": "PLAYED_CARDS",
    "data": [
      {
        "number": 14,
        "color": "CLUBS"
      }
    ]
  },
  {
    "broadcast": false,
    "sentTo": "bello#1",
    "messageType": "REQUEST_CARD",
    "data": [
      {
        "number": 14,
        "color": "CLUBS"
      }
    ]
  },
  {
    "broadcast": false,
    "receivedFrom": "bello#1",
    "messageType": "CHOOSE_CARD",
    "data": {
      "number": 9,
      "color": "SPADES"
    }
  },
  {
    "broadcast": true,
    "messageType": "PLAYED_CARDS",
    "data": [
      {
        "number": 14,
        "color": "CLUBS"
      },
      {
        "number": 9,
        "color": "SPADES"
      }
    ]
  },
  {
    "broadcast": false,
    "sentTo": "nadja#2",
    "messageType": "REQUEST_CARD",
    "data": [
      {
        "number": 14,
        "color": "CLUBS"
      },
      {
        "number": 9,
        "color": "SPADES"
      }
    ]
  },
  {
    "broadcast": false,
    "receivedFrom": "nadja#2",
    "messageType": "CHOOSE_CARD",
    "data": {
      "number": 11,
      "color": "SPADES"
    }
  },
  {
    "broadcast": true,
    "messageType": "PLAYED_CARDS",
    "data": [
      {
        "number": 14,
        "color": "CLUBS"
      },
      {
        "number": 9,
        "color": "SPADES"
      },
      {
        "number": 11,
        "color": "SPADES"
      }
    ]
  },
  {
    "broadcast": false,
    "sentTo": "bella#3",
    "messageType": "REQUEST_CARD",
    "data": [
      {
        "number": 14,
        "color": "CLUBS"
      },
      {
        "number": 9,
        "color": "SPADES"
      },
      {
        "number": 11,
        "color": "SPADES"
      }
    ]
  },
  {
    "broadcast": false,
    "receivedFrom": "bella#3",
    "messageType": "CHOOSE_CARD",
    "data": {
      "number": 14,
      "color": "SPADES"
    }
  },
  {
    "broadcast": true,
    "messageType": "PLAYED_CARDS",
    "data": [
      {
        "number": 14,
        "color": "CLUBS"
      },
      {
        "number": 9,
        "color": "SPADES"
      },
      {
        "number": 11,
        "color": "SPADES"
      },
      {
        "number": 14,
        "color": "SPADES"
      }
    ]
  },
  {
    "broadcast": true,
    "messageType": "BROADCAST_STICH",
    "data": {
      "name": "roman",
      "id": "93b80902-df6b-4f25-9c4e-590282b6c91f",
      "seatId": 0,
      "playedCards": [
        {
          "number": 14,
          "color": "CLUBS"
        },
        {
          "number": 9,
          "color": "SPADES"
        },
        {
          "number": 11,
          "color": "SPADES"
        },
        {
          "number": 14,
          "color": "SPADES"
        }
      ],
      "teams": [
        {
          "name": "Team 1",
          "points": 276,
          "currentRoundPoints": 276
        },
        {
          "name": "Team 2",
          "points": 0,
          "currentRoundPoints": 0
        }
      ]
    }
  },
  {
    "broadcast": false,
    "sentTo": "roman#0",
    "messageType": "REQUEST_CARD",
    "data": []
  },
  {
    "broadcast": false,
    "receivedFrom": "roman#0",
    "messageType": "CHOOSE_CARD",
    "data": {
      "number": 7,
      "color": "CLUBS"
    }
  },
  {
    "broadcast": true,
    "messageType": "PLAYED_CARDS",
    "data": [
      {
        "number": 7,
        "color": "CLUBS"
      }
    ]
  },
  {
    "broadcast": false,
    "sentTo": "bello#1",
    "messageType": "REQUEST_CARD",
    "data": [
      {
        "number": 7,
        "color": "CLUBS"
      }
    ]
  },
  {
    "broadcast": false,
    "receivedFrom": "bello#1",
    "messageType": "CHOOSE_CARD",
    "data": {
      "number": 9,
      "color": "HEARTS"
    }
  },
  {
    "broadcast": true,
    "messageType": "PLAYED_CARDS",
    "data": [
      {
        "number": 7,
        "color": "CLUBS"
      },
      {
        "number": 9,
        "color": "HEARTS"
      }
    ]
  },
  {
    "broadcast": false,
    "sentTo": "nadja#2",
    "messageType": "REQUEST_CARD",
    "data": [
      {
        "number": 7,
        "color": "CLUBS"
      },
      {
        "number": 9,
        "color": "HEARTS"
      }
    ]
  },
  {
    "broadcast": false,
    "receivedFrom": "nadja#2",
    "messageType": "CHOOSE_CARD",
    "data": {
      "number": 10,
      "color": "HEARTS"
    }
  },
  {
    "broadcast": true,
    "messageType": "PLAYED_CARDS",
    "data": [
      {
        "number": 7,
        "color": "CLUBS"
      },
      {
        "number": 9,
        "color": "HEARTS"
      },
      {
        "number": 10,
        "color": "HEARTS"
      }
    ]
  },
  {
    "broadcast": false,
    "sentTo": "bella#3",
    "messageType": "REQUEST_CARD",
    "data": [
      {
        "number": 7,
        "color": "CLUBS"
      },
      {
        "number": 9,
        "color": "HEARTS"
      },
      {
        "number": 10,
        "color": "HEARTS"
      }
    ]
  },
  {
    "broadcast": false,
    "receivedFrom": "bella#3",
    "messageType": "CHOOSE_CARD",
    "data": {
      "number": 13,
      "color": "HEARTS"
    }
  },
  {
    "broadcast": true,
    "messageType": "PLAYED_CARDS",
    "data": [
      {
        "number": 7,
        "color": "CLUBS"
      },
      {
        "number": 9,
        "color": "HEARTS"
      },
      {
        "number": 10,
        "color": "HEARTS"
      },
      {
        "number": 13,
        "color": "HEARTS"
      }
    ]
  },
  {
    "broadcast": true,
    "messageType": "BROADCAST_STICH",
    "data": {
      "name": "roman",
      "id": "93b80902-df6b-4f25-9c4e-590282b6c91f",
      "seatId": 0,
      "playedCards": [
        {
          "number": 7,
          "color": "CLUBS"
        },
        {
          "number": 9,
          "color": "HEARTS"
        },
        {
          "number": 10,
          "color": "HEARTS"
        },
        {
          "number": 13,
          "color": "HEARTS"
        }
      ],
      "teams": [
        {
          "name": "Team 1",
          "points": 304,
          "currentRoundPoints": 304
        },
        {
          "name": "Team 2",
          "points": 0,
          "currentRoundPoints": 0
        }
      ]
    }
  },
  {
    "broadcast": false,
    "sentTo": "roman#0",
    "messageType": "REQUEST_CARD",
    "data": []
  },
  {
    "broadcast": false,
    "receivedFrom": "roman#0",
    "messageType": "CHOOSE_CARD",
    "data": {
      "number": 6,
      "color": "CLUBS"
    }
  },
  {
    "broadcast": true,
    "messageType": "PLAYED_CARDS",
    "data": [
      {
        "number": 6,
        "color": "CLUBS"
      }
    ]
  },
  {
    "broadcast": false,
    "sentTo": "bello#1",
    "messageType": "REQUEST_CARD",
    "data": [
      {
        "number": 6,
        "color": "CLUBS"
      }
    ]
  },
  {
    "broadcast": false,
    "receivedFrom": "bello#1",
    "messageType": "CHOOSE_CARD",
    "data": {
      "number": 8,
      "color": "HEARTS"
    }
  },
  {
    "broadcast": true,
    "messageType": "PLAYED_CARDS",
    "data": [
      {
        "number": 6,
        "color": "CLUBS"
      },
      {
        "number": 8,
        "color": "HEARTS"
      }
    ]
  },
  {
    "broadcast": false,
    "sentTo": "nadja#2",
    "messageType": "REQUEST_CARD",
    "data": [
      {
        "number": 6,
        "color": "CLUBS"
      },
      {
        "number": 8,
        "color": "HEARTS"
      }
    ]
  },
  {
    "broadcast": false,
    "receivedFrom": "nadja#2",
    "messageType": "CHOOSE_CARD",
    "data": {
      "number": 7,
      "color": "HEARTS"
    }
  },
  {
    "broadcast": true,
    "messageType": "PLAYED_CARDS",
    "data": [
      {
        "number": 6,
        "color": "CLUBS"
      },
      {
        "number": 8,
        "color": "HEARTS"
      },
      {
        "number": 7,
        "color": "HEARTS"
      }
    ]
  },
  {
    "broadcast": false,
    "sentTo": "bella#3",
    "messageType": "REQUEST_CARD",
    "data": [
      {
        "number": 6,
        "color": "CLUBS"
      },
      {
        "number": 8,
        "color": "HEARTS"
      },
      {
        "number": 7,
        "color": "HEARTS"
      }
    ]
  },
  {
    "broadcast": false,
    "receivedFrom": "bella#3",
    "messageType": "CHOOSE_CARD",
    "data": {
      "number": 6,
      "color": "HEARTS"
    }
  },
  {
    "broadcast": true,
    "messageType": "PLAYED_CARDS",
    "data": [
      {
        "number": 6,
        "color": "CLUBS"
      },
      {
        "number": 8,
        "color": "HEARTS"
      },
      {
        "number": 7,
        "color": "HEARTS"
      },
      {
        "number": 6,
        "color": "HEARTS"
      }
    ]
  },
  {
    "broadcast": true,
    "messageType": "BROADCAST_STICH",
    "data": {
      "name": "roman",
      "id": "93b80902-df6b-4f25-9c4e-590282b6c91f",
      "seatId": 0,
      "playedCards": [
        {
          "number": 6,
          "color": "CLUBS"
        },
        {
          "number": 8,
          "color": "HEARTS"
        },
        {
          "number": 7,
          "color": "HEARTS"
        },
        {
          "number": 6,
          "color": "HEARTS"
        }
      ],
      "teams": [
        {
          "name": "Team 1",
          "points": 514,
          "currentRoundPoints": 514
        },
        {
          "name": "Team 2",
          "points": 0,
          "currentRoundPoints": 0
        }
      ]
    }
  },
  {
    "broadcast": true,
    "messageType": "BROADCAST_GAME_FINISHED",
    "data": [
      {
        "name": "Team 1",
        "points": 514,
        "currentRoundPoints": 514
      },
      {
        "name": "Team 2",
        "points": 0,
        "currentRoundPoints": 0
      }
    ]
  },
  {
    "broadcast": false,
    "sentTo": "roman#0",
    "messageType": "DEAL_CARDS",
    "data": [
      {
        "number": 7,
        "color": "DIAMONDS"
      },
      {
        "number": 6,
        "color": "DIAMONDS"
      },
      {
        "number": 8,
        "color": "DIAMONDS"
      },
      {
        "number": 9,
        "color": "DIAMONDS"
      },
      {
        "number": 10,
        "color": "DIAMONDS"
      },
      {
        "number": 11,
        "color": "DIAMONDS"
      },
      {
        "number": 12,
        "color": "DIAMONDS"
      },
      {
        "number": 13,
        "color": "DIAMONDS"
      },
      {
        "number": 14,
        "color": "DIAMONDS"
      }
    ]
  },
  {
    "broadcast": false,
    "sentTo": "bello#1",
    "messageType": "DEAL_CARDS",
    "data": [
      {
        "number": 6,
        "color": "HEARTS"
      },
      {
        "number": 8,
        "color": "HEARTS"
      },
      {
        "number": 8,
        "color": "SPADES"
      },
      {
        "number": 9,
        "color": "CLUBS"
      },
      {
        "number": 6,
        "color": "SPADES"
      },
      {
        "number": 9,
        "color": "HEARTS"
      },
      {
        "number": 9,
        "color": "SPADES"
      },
      {
        "number": 10,
        "color": "CLUBS"
      },
      {
        "number": 7,
        "color": "CLUBS"
      }
    ]
  },
  {
    "broadcast": false,
    "sentTo": "nadja#2",
    "messageType": "DEAL_CARDS",
    "data": [
      {
        "number": 10,
        "color": "HEARTS"
      },
      {
        "number": 10,
        "color": "SPADES"
      },
      {
        "number": 11,
        "color": "CLUBS"
      },
      {
        "number": 6,
        "color": "CLUBS"
      },
      {
        "number": 11,
        "color": "HEARTS"
      },
      {
        "number": 11,
        "color": "SPADES"
      },
      {
        "number": 12,
        "color": "CLUBS"
      },
      {
        "number": 7,
        "color": "HEARTS"
      },
      {
        "number": 12,
        "color": "HEARTS"
      }
    ]
  },
  {
    "broadcast": false,
    "sentTo": "bella#3",
    "messageType": "DEAL_CARDS",
    "data": [
      {
        "number": 12,
        "color": "SPADES"
      },
      {
        "number": 13,
        "color": "CLUBS"
      },
      {
        "number": 7,
        "color": "SPADES"
      },
      {
        "number": 13,
        "color": "HEARTS"
      },
      {
        "number": 13,
        "color": "SPADES"
      },
      {
        "number": 14,
        "color": "CLUBS"
      },
      {
        "number": 8,
        "color": "CLUBS"
      },
      {
        "number": 14,
        "color": "HEARTS"
      },
      {
        "number": 14,
        "color": "SPADES"
      }
    ]
  },
  {
    "broadcast": false,
    "sentTo": "bello#1",
    "messageType": "REQUEST_TRUMPF",
    "data": false
  },
  {
    "broadcast": false,
    "receivedFrom": "bello#1",
    "messageType": "CHOOSE_TRUMPF",
    "data": {
      "mode": "TRUMPF",
      "trumpfColor": "DIAMONDS"
    }
  },
  {
    "broadcast": true,
    "messageType": "BROADCAST_TRUMPF",
    "data": {
      "mode": "TRUMPF",
      "trumpfColor": "DIAMONDS"
    }
  },
  {
    "broadcast": false,
    "sentTo": "bello#1",
    "messageType": "REQUEST_CARD",
    "data": []
  },
  {
    "broadcast": false,
    "receivedFrom": "bello#1",
    "messageType": "CHOOSE_CARD",
    "data": {
      "number": 10,
      "color": "CLUBS"
    }
  },
  {
    "broadcast": true,
    "messageType": "PLAYED_CARDS",
    "data": [
      {
        "number": 10,
        "color": "CLUBS"
      }
    ]
  },
  {
    "broadcast": false,
    "sentTo": "nadja#2",
    "messageType": "REQUEST_CARD",
    "data": [
      {
        "number": 10,
        "color": "CLUBS"
      }
    ]
  },
  {
    "broadcast": false,
    "receivedFrom": "nadja#2",
    "messageType": "CHOOSE_CARD",
    "data": {
      "number": 11,
      "color": "CLUBS"
    }
  },
  {
    "broadcast": true,
    "messageType": "PLAYED_CARDS",
    "data": [
      {
        "number": 10,
        "color": "CLUBS"
      },
      {
        "number": 11,
        "color": "CLUBS"
      }
    ]
  },
  {
    "broadcast": false,
    "sentTo": "bella#3",
    "messageType": "REQUEST_CARD",
    "data": [
      {
        "number": 10,
        "color": "CLUBS"
      },
      {
        "number": 11,
        "color": "CLUBS"
      }
    ]
  },
  {
    "broadcast": false,
    "receivedFrom": "bella#3",
    "messageType": "CHOOSE_CARD",
    "data": {
      "number": 14,
      "color": "CLUBS"
    }
  },
  {
    "broadcast": true,
    "messageType": "PLAYED_CARDS",
    "data": [
      {
        "number": 10,
        "color": "CLUBS"
      },
      {
        "number": 11,
        "color": "CLUBS"
      },
      {
        "number": 14,
        "color": "CLUBS"
      }
    ]
  },
  {
    "broadcast": false,
    "sentTo": "roman#0",
    "messageType": "REQUEST_CARD",
    "data": [
      {
        "number": 10,
        "color": "CLUBS"
      },
      {
        "number": 11,
        "color": "CLUBS"
      },
      {
        "number": 14,
        "color": "CLUBS"
      }
    ]
  },
  {
    "broadcast": false,
    "receivedFrom": "roman#0",
    "messageType": "CHOOSE_CARD",
    "data": {
      "number": 11,
      "color": "DIAMONDS"
    }
  },
  {
    "broadcast": true,
    "messageType": "PLAYED_CARDS",
    "data": [
      {
        "number": 10,
        "color": "CLUBS"
      },
      {
        "number": 11,
        "color": "CLUBS"
      },
      {
        "number": 14,
        "color": "CLUBS"
      },
      {
        "number": 11,
        "color": "DIAMONDS"
      }
    ]
  },
  {
    "broadcast": true,
    "messageType": "BROADCAST_STICH",
    "data": {
      "name": "roman",
      "id": "93b80902-df6b-4f25-9c4e-590282b6c91f",
      "seatId": 0,
      "playedCards": [
        {
          "number": 10,
          "color": "CLUBS"
        },
        {
          "number": 11,
          "color": "CLUBS"
        },
        {
          "number": 14,
          "color": "CLUBS"
        },
        {
          "number": 11,
          "color": "DIAMONDS"
        }
      ],
      "teams": [
        {
          "name": "Team 1",
          "points": 557,
          "currentRoundPoints": 43
        },
        {
          "name": "Team 2",
          "points": 0,
          "currentRoundPoints": 0
        }
      ]
    }
  },
  {
    "broadcast": false,
    "sentTo": "roman#0",
    "messageType": "REQUEST_CARD",
    "data": []
  },
  {
    "broadcast": false,
    "receivedFrom": "roman#0",
    "messageType": "CHOOSE_CARD",
    "data": {
      "number": 10,
      "color": "DIAMONDS"
    }
  },
  {
    "broadcast": true,
    "messageType": "PLAYED_CARDS",
    "data": [
      {
        "number": 10,
        "color": "DIAMONDS"
      }
    ]
  },
  {
    "broadcast": false,
    "sentTo": "bello#1",
    "messageType": "REQUEST_CARD",
    "data": [
      {
        "number": 10,
        "color": "DIAMONDS"
      }
    ]
  },
  {
    "broadcast": false,
    "receivedFrom": "bello#1",
    "messageType": "CHOOSE_CARD",
    "data": {
      "number": 9,
      "color": "CLUBS"
    }
  },
  {
    "broadcast": true,
    "messageType": "PLAYED_CARDS",
    "data": [
      {
        "number": 10,
        "color": "DIAMONDS"
      },
      {
        "number": 9,
        "color": "CLUBS"
      }
    ]
  },
  {
    "broadcast": false,
    "sentTo": "nadja#2",
    "messageType": "REQUEST_CARD",
    "data": [
      {
        "number": 10,
        "color": "DIAMONDS"
      },
      {
        "number": 9,
        "color": "CLUBS"
      }
    ]
  },
  {
    "broadcast": false,
    "receivedFrom": "nadja#2",
    "messageType": "CHOOSE_CARD",
    "data": {
      "number": 6,
      "color": "CLUBS"
    }
  },
  {
    "broadcast": true,
    "messageType": "PLAYED_CARDS",
    "data": [
      {
        "number": 10,
        "color": "DIAMONDS"
      },
      {
        "number": 9,
        "color": "CLUBS"
      },
      {
        "number": 6,
        "color": "CLUBS"
      }
    ]
  },
  {
    "broadcast": false,
    "sentTo": "bella#3",
    "messageType": "REQUEST_CARD",
    "data": [
      {
        "number": 10,
        "color": "DIAMONDS"
      },
      {
        "number": 9,
        "color": "CLUBS"
      },
      {
        "number": 6,
        "color": "CLUBS"
      }
    ]
  },
  {
    "broadcast": false,
    "receivedFrom": "bella#3",
    "messageType": "CHOOSE_CARD",
    "data": {
      "number": 7,
      "color": "SPADES"
    }
  },
  {
    "broadcast": true,
    "messageType": "PLAYED_CARDS",
    "data": [
      {
        "number": 10,
        "color": "DIAMONDS"
      },
      {
        "number": 9,
        "color": "CLUBS"
      },
      {
        "number": 6,
        "color": "CLUBS"
      },
      {
        "number": 7,
        "color": "SPADES"
      }
    ]
  },
  {
    "broadcast": true,
    "messageType": "BROADCAST_STICH",
    "data": {
      "name": "roman",
      "id": "93b80902-df6b-4f25-9c4e-590282b6c91f",
      "seatId": 0,
      "playedCards": [
        {
          "number": 10,
          "color": "DIAMONDS"
        },
        {
          "number": 9,
          "color": "CLUBS"
        },
        {
          "number": 6,
          "color": "CLUBS"
        },
        {
          "number": 7,
          "color": "SPADES"
        }
      ],
      "teams": [
        {
          "name": "Team 1",
          "points": 567,
          "currentRoundPoints": 53
        },
        {
          "name": "Team 2",
          "points": 0,
          "currentRoundPoints": 0
        }
      ]
    }
  },
  {
    "broadcast": false,
    "sentTo": "roman#0",
    "messageType": "REQUEST_CARD",
    "data": []
  },
  {
    "broadcast": false,
    "receivedFrom": "roman#0",
    "messageType": "CHOOSE_CARD",
    "data": {
      "number": 12,
      "color": "DIAMONDS"
    }
  },
  {
    "broadcast": true,
    "messageType": "PLAYED_CARDS",
    "data": [
      {
        "number": 12,
        "color": "DIAMONDS"
      }
    ]
  },
  {
    "broadcast": false,
    "sentTo": "bello#1",
    "messageType": "REQUEST_CARD",
    "data": [
      {
        "number": 12,
        "color": "DIAMONDS"
      }
    ]
  },
  {
    "broadcast": false,
    "receivedFrom": "bello#1",
    "messageType": "CHOOSE_CARD",
    "data": {
      "number": 6,
      "color": "SPADES"
    }
  },
  {
    "broadcast": true,
    "messageType": "PLAYED_CARDS",
    "data": [
      {
        "number": 12,
        "color": "DIAMONDS"
      },
      {
        "number": 6,
        "color": "SPADES"
      }
    ]
  },
  {
    "broadcast": false,
    "sentTo": "nadja#2",
    "messageType": "REQUEST_CARD",
    "data": [
      {
        "number": 12,
        "color": "DIAMONDS"
      },
      {
        "number": 6,
        "color": "SPADES"
      }
    ]
  },
  {
    "broadcast": false,
    "receivedFrom": "nadja#2",
    "messageType": "CHOOSE_CARD",
    "data": {
      "number": 12,
      "color": "CLUBS"
    }
  },
  {
    "broadcast": true,
    "messageType": "PLAYED_CARDS",
    "data": [
      {
        "number": 12,
        "color": "DIAMONDS"
      },
      {
        "number": 6,
        "color": "SPADES"
      },
      {
        "number": 12,
        "color": "CLUBS"
      }
    ]
  },
  {
    "broadcast": false,
    "sentTo": "bella#3",
    "messageType": "REQUEST_CARD",
    "data": [
      {
        "number": 12,
        "color": "DIAMONDS"
      },
      {
        "number": 6,
        "color": "SPADES"
      },
      {
        "number": 12,
        "color": "CLUBS"
      }
    ]
  },
  {
    "broadcast": false,
    "receivedFrom": "bella#3",
    "messageType": "CHOOSE_CARD",
    "data": {
      "number": 12,
      "color": "SPADES"
    }
  },
  {
    "broadcast": true,
    "messageType": "PLAYED_CARDS",
    "data": [
      {
        "number": 12,
        "color": "DIAMONDS"
      },
      {
        "number": 6,
        "color": "SPADES"
      },
      {
        "number": 12,
        "color": "CLUBS"
      },
      {
        "number": 12,
        "color": "SPADES"
      }
    ]
  },
  {
    "broadcast": true,
    "messageType": "BROADCAST_STICH",
    "data": {
      "name": "roman",
      "id": "93b80902-df6b-4f25-9c4e-590282b6c91f",
      "seatId": 0,
      "playedCards": [
        {
          "number": 12,
          "color": "DIAMONDS"
        },
        {
          "number": 6,
          "color": "SPADES"
        },
        {
          "number": 12,
          "color": "CLUBS"
        },
        {
          "number": 12,
          "color": "SPADES"
        }
      ],
      "teams": [
        {
          "name": "Team 1",
          "points": 576,
          "currentRoundPoints": 62
        },
        {
          "name": "Team 2",
          "points": 0,
          "currentRoundPoints": 0
        }
      ]
    }
  },
  {
    "broadcast": false,
    "sentTo": "roman#0",
    "messageType": "REQUEST_CARD",
    "data": []
  },
  {
    "broadcast": false,
    "receivedFrom": "roman#0",
    "messageType": "CHOOSE_CARD",
    "data": {
      "number": 9,
      "color": "DIAMONDS"
    }
  },
  {
    "broadcast": true,
    "messageType": "PLAYED_CARDS",
    "data": [
      {
        "number": 9,
        "color": "DIAMONDS"
      }
    ]
  },
  {
    "broadcast": false,
    "sentTo": "bello#1",
    "messageType": "REQUEST_CARD",
    "data": [
      {
        "number": 9,
        "color": "DIAMONDS"
      }
    ]
  },
  {
    "broadcast": false,
    "receivedFrom": "bello#1",
    "messageType": "CHOOSE_CARD",
    "data": {
      "number": 7,
      "color": "CLUBS"
    }
  },
  {
    "broadcast": true,
    "messageType": "PLAYED_CARDS",
    "data": [
      {
        "number": 9,
        "color": "DIAMONDS"
      },
      {
        "number": 7,
        "color": "CLUBS"
      }
    ]
  },
  {
    "broadcast": false,
    "sentTo": "nadja#2",
    "messageType": "REQUEST_CARD",
    "data": [
      {
        "number": 9,
        "color": "DIAMONDS"
      },
      {
        "number": 7,
        "color": "CLUBS"
      }
    ]
  },
  {
    "broadcast": false,
    "receivedFrom": "nadja#2",
    "messageType": "CHOOSE_CARD",
    "data": {
      "number": 12,
      "color": "HEARTS"
    }
  },
  {
    "broadcast": true,
    "messageType": "PLAYED_CARDS",
    "data": [
      {
        "number": 9,
        "color": "DIAMONDS"
      },
      {
        "number": 7,
        "color": "CLUBS"
      },
      {
        "number": 12,
        "color": "HEARTS"
      }
    ]
  },
  {
    "broadcast": false,
    "sentTo": "bella#3",
    "messageType": "REQUEST_CARD",
    "data": [
      {
        "number": 9,
        "color": "DIAMONDS"
      },
      {
        "number": 7,
        "color": "CLUBS"
      },
      {
        "number": 12,
        "color": "HEARTS"
      }
    ]
  },
  {
    "broadcast": false,
    "receivedFrom": "bella#3",
    "messageType": "CHOOSE_CARD",
    "data": {
      "number": 13,
      "color": "CLUBS"
    }
  },
  {
    "broadcast": true,
    "messageType": "PLAYED_CARDS",
    "data": [
      {
        "number": 9,
        "color": "DIAMONDS"
      },
      {
        "number": 7,
        "color": "CLUBS"
      },
      {
        "number": 12,
        "color": "HEARTS"
      },
      {
        "number": 13,
        "color": "CLUBS"
      }
    ]
  },
  {
    "broadcast": true,
    "messageType": "BROADCAST_STICH",
    "data": {
      "name": "roman",
      "id": "93b80902-df6b-4f25-9c4e-590282b6c91f",
      "seatId": 0,
      "playedCards": [
        {
          "number": 9,
          "color": "DIAMONDS"
        },
        {
          "number": 7,
          "color": "CLUBS"
        },
        {
          "number": 12,
          "color": "HEARTS"
        },
        {
          "number": 13,
          "color": "CLUBS"
        }
      ],
      "teams": [
        {
          "name": "Team 1",
          "points": 597,
          "currentRoundPoints": 83
        },
        {
          "name": "Team 2",
          "points": 0,
          "currentRoundPoints": 0
        }
      ]
    }
  },
  {
    "broadcast": false,
    "sentTo": "roman#0",
    "messageType": "REQUEST_CARD",
    "data": []
  },
  {
    "broadcast": false,
    "receivedFrom": "roman#0",
    "messageType": "CHOOSE_CARD",
    "data": {
      "number": 8,
      "color": "DIAMONDS"
    }
  },
  {
    "broadcast": true,
    "messageType": "PLAYED_CARDS",
    "data": [
      {
        "number": 8,
        "color": "DIAMONDS"
      }
    ]
  },
  {
    "broadcast": false,
    "sentTo": "bello#1",
    "messageType": "REQUEST_CARD",
    "data": [
      {
        "number": 8,
        "color": "DIAMONDS"
      }
    ]
  },
  {
    "broadcast": false,
    "receivedFrom": "bello#1",
    "messageType": "CHOOSE_CARD",
    "data": {
      "number": 9,
      "color": "HEARTS"
    }
  },
  {
    "broadcast": true,
    "messageType": "PLAYED_CARDS",
    "data": [
      {
        "number": 8,
        "color": "DIAMONDS"
      },
      {
        "number": 9,
        "color": "HEARTS"
      }
    ]
  },
  {
    "broadcast": false,
    "sentTo": "nadja#2",
    "messageType": "REQUEST_CARD",
    "data": [
      {
        "number": 8,
        "color": "DIAMONDS"
      },
      {
        "number": 9,
        "color": "HEARTS"
      }
    ]
  },
  {
    "broadcast": false,
    "receivedFrom": "nadja#2",
    "messageType": "CHOOSE_CARD",
    "data": {
      "number": 11,
      "color": "HEARTS"
    }
  },
  {
    "broadcast": true,
    "messageType": "PLAYED_CARDS",
    "data": [
      {
        "number": 8,
        "color": "DIAMONDS"
      },
      {
        "number": 9,
        "color": "HEARTS"
      },
      {
        "number": 11,
        "color": "HEARTS"
      }
    ]
  },
  {
    "broadcast": false,
    "sentTo": "bella#3",
    "messageType": "REQUEST_CARD",
    "data": [
      {
        "number": 8,
        "color": "DIAMONDS"
      },
      {
        "number": 9,
        "color": "HEARTS"
      },
      {
        "number": 11,
        "color": "HEARTS"
      }
    ]
  },
  {
    "broadcast": false,
    "receivedFrom": "bella#3",
    "messageType": "CHOOSE_CARD",
    "data": {
      "number": 8,
      "color": "CLUBS"
    }
  },
  {
    "broadcast": true,
    "messageType": "PLAYED_CARDS",
    "data": [
      {
        "number": 8,
        "color": "DIAMONDS"
      },
      {
        "number": 9,
        "color": "HEARTS"
      },
      {
        "number": 11,
        "color": "HEARTS"
      },
      {
        "number": 8,
        "color": "CLUBS"
      }
    ]
  },
  {
    "broadcast": true,
    "messageType": "BROADCAST_STICH",
    "data": {
      "name": "roman",
      "id": "93b80902-df6b-4f25-9c4e-590282b6c91f",
      "seatId": 0,
      "playedCards": [
        {
          "number": 8,
          "color": "DIAMONDS"
        },
        {
          "number": 9,
          "color": "HEARTS"
        },
        {
          "number": 11,
          "color": "HEARTS"
        },
        {
          "number": 8,
          "color": "CLUBS"
        }
      ],
      "teams": [
        {
          "name": "Team 1",
          "points": 599,
          "currentRoundPoints": 85
        },
        {
          "name": "Team 2",
          "points": 0,
          "currentRoundPoints": 0
        }
      ]
    }
  },
  {
    "broadcast": false,
    "sentTo": "roman#0",
    "messageType": "REQUEST_CARD",
    "data": []
  },
  {
    "broadcast": false,
    "receivedFrom": "roman#0",
    "messageType": "CHOOSE_CARD",
    "data": {
      "number": 13,
      "color": "DIAMONDS"
    }
  },
  {
    "broadcast": true,
    "messageType": "PLAYED_CARDS",
    "data": [
      {
        "number": 13,
        "color": "DIAMONDS"
      }
    ]
  },
  {
    "broadcast": false,
    "sentTo": "bello#1",
    "messageType": "REQUEST_CARD",
    "data": [
      {
        "number": 13,
        "color": "DIAMONDS"
      }
    ]
  },
  {
    "broadcast": false,
    "receivedFrom": "bello#1",
    "messageType": "CHOOSE_CARD",
    "data": {
      "number": 8,
      "color": "SPADES"
    }
  },
  {
    "broadcast": true,
    "messageType": "PLAYED_CARDS",
    "data": [
      {
        "number": 13,
        "color": "DIAMONDS"
      },
      {
        "number": 8,
        "color": "SPADES"
      }
    ]
  },
  {
    "broadcast": false,
    "sentTo": "nadja#2",
    "messageType": "REQUEST_CARD",
    "data": [
      {
        "number": 13,
        "color": "DIAMONDS"
      },
      {
        "number": 8,
        "color": "SPADES"
      }
    ]
  },
  {
    "broadcast": false,
    "receivedFrom": "nadja#2",
    "messageType": "CHOOSE_CARD",
    "data": {
      "number": 10,
      "color": "SPADES"
    }
  },
  {
    "broadcast": true,
    "messageType": "PLAYED_CARDS",
    "data": [
      {
        "number": 13,
        "color": "DIAMONDS"
      },
      {
        "number": 8,
        "color": "SPADES"
      },
      {
        "number": 10,
        "color": "SPADES"
      }
    ]
  },
  {
    "broadcast": false,
    "sentTo": "bella#3",
    "messageType": "REQUEST_CARD",
    "data": [
      {
        "number": 13,
        "color": "DIAMONDS"
      },
      {
        "number": 8,
        "color": "SPADES"
      },
      {
        "number": 10,
        "color": "SPADES"
      }
    ]
  },
  {
    "broadcast": false,
    "receivedFrom": "bella#3",
    "messageType": "CHOOSE_CARD",
    "data": {
      "number": 13,
      "color": "SPADES"
    }
  },
  {
    "broadcast": true,
    "messageType": "PLAYED_CARDS",
    "data": [
      {
        "number": 13,
        "color": "DIAMONDS"
      },
      {
        "number": 8,
        "color": "SPADES"
      },
      {
        "number": 10,
        "color": "SPADES"
      },
      {
        "number": 13,
        "color": "SPADES"
      }
    ]
  },
  {
    "broadcast": true,
    "messageType": "BROADCAST_STICH",
    "data": {
      "name": "roman",
      "id": "93b80902-df6b-4f25-9c4e-590282b6c91f",
      "seatId": 0,
      "playedCards": [
        {
          "number": 13,
          "color": "DIAMONDS"
        },
        {
          "number": 8,
          "color": "SPADES"
        },
        {
          "number": 10,
          "color": "SPADES"
        },
        {
          "number": 13,
          "color": "SPADES"
        }
      ],
      "teams": [
        {
          "name": "Team 1",
          "points": 617,
          "currentRoundPoints": 103
        },
        {
          "name": "Team 2",
          "points": 0,
          "currentRoundPoints": 0
        }
      ]
    }
  },
  {
    "broadcast": false,
    "sentTo": "roman#0",
    "messageType": "REQUEST_CARD",
    "data": []
  },
  {
    "broadcast": false,
    "receivedFrom": "roman#0",
    "messageType": "CHOOSE_CARD",
    "data": {
      "number": 7,
      "color": "DIAMONDS"
    }
  },
  {
    "broadcast": true,
    "messageType": "PLAYED_CARDS",
    "data": [
      {
        "number": 7,
        "color": "DIAMONDS"
      }
    ]
  },
  {
    "broadcast": false,
    "sentTo": "bello#1",
    "messageType": "REQUEST_CARD",
    "data": [
      {
        "number": 7,
        "color": "DIAMONDS"
      }
    ]
  },
  {
    "broadcast": false,
    "receivedFrom": "bello#1",
    "messageType": "CHOOSE_CARD",
    "data": {
      "number": 8,
      "color": "HEARTS"
    }
  },
  {
    "broadcast": true,
    "messageType": "PLAYED_CARDS",
    "data": [
      {
        "number": 7,
        "color": "DIAMONDS"
      },
      {
        "number": 8,
        "color": "HEARTS"
      }
    ]
  },
  {
    "broadcast": false,
    "sentTo": "nadja#2",
    "messageType": "REQUEST_CARD",
    "data": [
      {
        "number": 7,
        "color": "DIAMONDS"
      },
      {
        "number": 8,
        "color": "HEARTS"
      }
    ]
  },
  {
    "broadcast": false,
    "receivedFrom": "nadja#2",
    "messageType": "CHOOSE_CARD",
    "data": {
      "number": 10,
      "color": "HEARTS"
    }
  },
  {
    "broadcast": true,
    "messageType": "PLAYED_CARDS",
    "data": [
      {
        "number": 7,
        "color": "DIAMONDS"
      },
      {
        "number": 8,
        "color": "HEARTS"
      },
      {
        "number": 10,
        "color": "HEARTS"
      }
    ]
  },
  {
    "broadcast": false,
    "sentTo": "bella#3",
    "messageType": "REQUEST_CARD",
    "data": [
      {
        "number": 7,
        "color": "DIAMONDS"
      },
      {
        "number": 8,
        "color": "HEARTS"
      },
      {
        "number": 10,
        "color": "HEARTS"
      }
    ]
  },
  {
    "broadcast": false,
    "receivedFrom": "bella#3",
    "messageType": "CHOOSE_CARD",
    "data": {
      "number": 14,
      "color": "HEARTS"
    }
  },
  {
    "broadcast": true,
    "messageType": "PLAYED_CARDS",
    "data": [
      {
        "number": 7,
        "color": "DIAMONDS"
      },
      {
        "number": 8,
        "color": "HEARTS"
      },
      {
        "number": 10,
        "color": "HEARTS"
      },
      {
        "number": 14,
        "color": "HEARTS"
      }
    ]
  },
  {
    "broadcast": true,
    "messageType": "BROADCAST_STICH",
    "data": {
      "name": "roman",
      "id": "93b80902-df6b-4f25-9c4e-590282b6c91f",
      "seatId": 0,
      "playedCards": [
        {
          "number": 7,
          "color": "DIAMONDS"
        },
        {
          "number": 8,
          "color": "HEARTS"
        },
        {
          "number": 10,
          "color": "HEARTS"
        },
        {
          "number": 14,
          "color": "HEARTS"
        }
      ],
      "teams": [
        {
          "name": "Team 1",
          "points": 638,
          "currentRoundPoints": 124
        },
        {
          "name": "Team 2",
          "points": 0,
          "currentRoundPoints": 0
        }
      ]
    }
  },
  {
    "broadcast": false,
    "sentTo": "roman#0",
    "messageType": "REQUEST_CARD",
    "data": []
  },
  {
    "broadcast": false,
    "receivedFrom": "roman#0",
    "messageType": "CHOOSE_CARD",
    "data": {
      "number": 14,
      "color": "DIAMONDS"
    }
  },
  {
    "broadcast": true,
    "messageType": "PLAYED_CARDS",
    "data": [
      {
        "number": 14,
        "color": "DIAMONDS"
      }
    ]
  },
  {
    "broadcast": false,
    "sentTo": "bello#1",
    "messageType": "REQUEST_CARD",
    "data": [
      {
        "number": 14,
        "color": "DIAMONDS"
      }
    ]
  },
  {
    "broadcast": false,
    "receivedFrom": "bello#1",
    "messageType": "CHOOSE_CARD",
    "data": {
      "number": 9,
      "color": "SPADES"
    }
  },
  {
    "broadcast": true,
    "messageType": "PLAYED_CARDS",
    "data": [
      {
        "number": 14,
        "color": "DIAMONDS"
      },
      {
        "number": 9,
        "color": "SPADES"
      }
    ]
  },
  {
    "broadcast": false,
    "sentTo": "nadja#2",
    "messageType": "REQUEST_CARD",
    "data": [
      {
        "number": 14,
        "color": "DIAMONDS"
      },
      {
        "number": 9,
        "color": "SPADES"
      }
    ]
  },
  {
    "broadcast": false,
    "receivedFrom": "nadja#2",
    "messageType": "CHOOSE_CARD",
    "data": {
      "number": 11,
      "color": "SPADES"
    }
  },
  {
    "broadcast": true,
    "messageType": "PLAYED_CARDS",
    "data": [
      {
        "number": 14,
        "color": "DIAMONDS"
      },
      {
        "number": 9,
        "color": "SPADES"
      },
      {
        "number": 11,
        "color": "SPADES"
      }
    ]
  },
  {
    "broadcast": false,
    "sentTo": "bella#3",
    "messageType": "REQUEST_CARD",
    "data": [
      {
        "number": 14,
        "color": "DIAMONDS"
      },
      {
        "number": 9,
        "color": "SPADES"
      },
      {
        "number": 11,
        "color": "SPADES"
      }
    ]
  },
  {
    "broadcast": false,
    "receivedFrom": "bella#3",
    "messageType": "CHOOSE_CARD",
    "data": {
      "number": 14,
      "color": "SPADES"
    }
  },
  {
    "broadcast": true,
    "messageType": "PLAYED_CARDS",
    "data": [
      {
        "number": 14,
        "color": "DIAMONDS"
      },
      {
        "number": 9,
        "color": "SPADES"
      },
      {
        "number": 11,
        "color": "SPADES"
      },
      {
        "number": 14,
        "color": "SPADES"
      }
    ]
  },
  {
    "broadcast": true,
    "messageType": "BROADCAST_STICH",
    "data": {
      "name": "roman",
      "id": "93b80902-df6b-4f25-9c4e-590282b6c91f",
      "seatId": 0,
      "playedCards": [
        {
          "number": 14,
          "color": "DIAMONDS"
        },
        {
          "number": 9,
          "color": "SPADES"
        },
        {
          "number": 11,
          "color": "SPADES"
        },
        {
          "number": 14,
          "color": "SPADES"
        }
      ],
      "teams": [
        {
          "name": "Team 1",
          "points": 662,
          "currentRoundPoints": 148
        },
        {
          "name": "Team 2",
          "points": 0,
          "currentRoundPoints": 0
        }
      ]
    }
  },
  {
    "broadcast": false,
    "sentTo": "roman#0",
    "messageType": "REQUEST_CARD",
    "data": []
  },
  {
    "broadcast": false,
    "receivedFrom": "roman#0",
    "messageType": "CHOOSE_CARD",
    "data": {
      "number": 6,
      "color": "DIAMONDS"
    }
  },
  {
    "broadcast": true,
    "messageType": "PLAYED_CARDS",
    "data": [
      {
        "number": 6,
        "color": "DIAMONDS"
      }
    ]
  },
  {
    "broadcast": false,
    "sentTo": "bello#1",
    "messageType": "REQUEST_CARD",
    "data": [
      {
        "number": 6,
        "color": "DIAMONDS"
      }
    ]
  },
  {
    "broadcast": false,
    "receivedFrom": "bello#1",
    "messageType": "CHOOSE_CARD",
    "data": {
      "number": 6,
      "color": "HEARTS"
    }
  },
  {
    "broadcast": true,
    "messageType": "PLAYED_CARDS",
    "data": [
      {
        "number": 6,
        "color": "DIAMONDS"
      },
      {
        "number": 6,
        "color": "HEARTS"
      }
    ]
  },
  {
    "broadcast": false,
    "sentTo": "nadja#2",
    "messageType": "REQUEST_CARD",
    "data": [
      {
        "number": 6,
        "color": "DIAMONDS"
      },
      {
        "number": 6,
        "color": "HEARTS"
      }
    ]
  },
  {
    "broadcast": false,
    "receivedFrom": "nadja#2",
    "messageType": "CHOOSE_CARD",
    "data": {
      "number": 7,
      "color": "HEARTS"
    }
  },
  {
    "broadcast": true,
    "messageType": "PLAYED_CARDS",
    "data": [
      {
        "number": 6,
        "color": "DIAMONDS"
      },
      {
        "number": 6,
        "color": "HEARTS"
      },
      {
        "number": 7,
        "color": "HEARTS"
      }
    ]
  },
  {
    "broadcast": false,
    "sentTo": "bella#3",
    "messageType": "REQUEST_CARD",
    "data": [
      {
        "number": 6,
        "color": "DIAMONDS"
      },
      {
        "number": 6,
        "color": "HEARTS"
      },
      {
        "number": 7,
        "color": "HEARTS"
      }
    ]
  },
  {
    "broadcast": false,
    "receivedFrom": "bella#3",
    "messageType": "CHOOSE_CARD",
    "data": {
      "number": 13,
      "color": "HEARTS"
    }
  },
  {
    "broadcast": true,
    "messageType": "PLAYED_CARDS",
    "data": [
      {
        "number": 6,
        "color": "DIAMONDS"
      },
      {
        "number": 6,
        "color": "HEARTS"
      },
      {
        "number": 7,
        "color": "HEARTS"
      },
      {
        "number": 13,
        "color": "HEARTS"
      }
    ]
  },
  {
    "broadcast": true,
    "messageType": "BROADCAST_STICH",
    "data": {
      "name": "roman",
      "id": "93b80902-df6b-4f25-9c4e-590282b6c91f",
      "seatId": 0,
      "playedCards": [
        {
          "number": 6,
          "color": "DIAMONDS"
        },
        {
          "number": 6,
          "color": "HEARTS"
        },
        {
          "number": 7,
          "color": "HEARTS"
        },
        {
          "number": 13,
          "color": "HEARTS"
        }
      ],
      "teams": [
        {
          "name": "Team 1",
          "points": 771,
          "currentRoundPoints": 257
        },
        {
          "name": "Team 2",
          "points": 0,
          "currentRoundPoints": 0
        }
      ]
    }
  },
  {
    "broadcast": true,
    "messageType": "BROADCAST_GAME_FINISHED",
    "data": [
      {
        "name": "Team 1",
        "points": 771,
        "currentRoundPoints": 257
      },
      {
        "name": "Team 2",
        "points": 0,
        "currentRoundPoints": 0
      }
    ]
  },
  {
    "broadcast": true,
    "messageType": "BROADCAST_WINNER_TEAM",
    "data": {
      "name": "Team 1",
      "points": 771,
      "currentRoundPoints": 0
    }
  }
]