[{"broadcast":true,"messageType":"BROADCAST_TEAMS","data":[{"name":"Team 1","players":[{"name":"roman","id":"5f81f8c3-d456-4ce6-a094-1bf83f8909b8","seatId":0},{"name":"Computer","id":"d0705f78-4713-41e8-a54b-d242d3f63a0e","seatId":2}]},{"name":"Team 2","players":[{"name":"Computer","id":"6f661d6d-a8fd-48b2-b9df-8b73278fafcc","seatId":1},{"name":"Computer","id":"d5b7d243-72cc-4492-a9db-5b68e6bf62d1","seatId":3}]}]},{"broadcast":true,"messageType":"BROADCAST_GAMESTATE","data":{"version":"V0.2","trump":-1,"dealer":1,"currentPlayer":0,"playerView":0,"forehand":-1,"tricks":[],"player":[{"hand":[]},{"hand":[]},{"hand":[]},{"hand":[]}],"jassTyp":"SCHIEBER","gameId":0}},{"broadcast":false,"sentTo":"roman#0","messageType":"DEAL_CARDS","data":[{"number":11,"color":"SPADES"},{"number":13,"color":"HEARTS"},{"number":11,"color":"DIAMONDS"},{"number":9,"color":"HEARTS"},{"number":12,"color":"DIAMONDS"},{"number":12,"color":"CLUBS"},{"number":8,"color":"DIAMONDS"},{"number":10,"color":"CLUBS"},{"number":7,"color":"DIAMONDS"}]},{"broadcast":false,"sentTo":"Computer#1","messageType":"DEAL_CARDS","data":[{"number":14,"color":"SPADES"},{"number":7,"color":"CLUBS"},{"number":7,"color":"SPADES"},{"number":6,"color":"CLUBS"},{"number":13,"color":"CLUBS"},{"number":14,"color":"DIAMONDS"},{"number":9,"color":"CLUBS"},{"number":13,"color":"DIAMONDS"},{"number":11,"color":"CLUBS"}]},{"broadcast":false,"sentTo":"Computer#2","messageType":"DEAL_CARDS","data":[{"number":10,"color":"SPADES"},{"number":6,"color":"HEARTS"},{"number":10,"color":"DIAMONDS"},{"number":9,"color":"DIAMONDS"},{"number":7,"color":"HEARTS"},{"number":6,"color":"DIAMONDS"},{"number":14,"color":"HEARTS"},{"number":9,"color":"SPADES"},{"number":10,"color":"HEARTS"}]},{"broadcast":false,"sentTo":"Computer#3","messageType":"DEAL_CARDS","data":[{"number":14,"color":"CLUBS"},{"number":12,"color":"HEARTS"},{"number":8,"color":"SPADES"},{"number":12,"color":"SPADES"},{"number":11,"color":"HEARTS"},{"number":6,"color":"SPADES"},{"number":8,"color":"HEARTS"},{"number":13,"color":"SPADES"},{"number":8,"color":"CLUBS"}]},{"broadcast":true,"messageType":"BROADCAST_GAMESTATE","data":{"version":"V0.2","trump":-1,"dealer":1,"currentPlayer":0,"playerView":0,"forehand":-1,"tricks":[],"player":[{"hand":["SJ","HK","DJ","H9","DQ","CQ","D8","C10","D7"]},{"hand":[]},{"hand":[]},{"hand":[]}],"jassTyp":"SCHIEBER","gameId":0}},{"broadcast":false,"sentTo":"roman#0","messageType":"REQUEST_TRUMPF","data":false},{"broadcast":false,"receivedFrom":"roman#0","messageType":"CHOOSE_TRUMPF","data":{"mode":"TRUMPF","trumpfColor":"DIAMONDS"}},{"broadcast":true,"messageType":"BROADCAST_TRUMPF","data":{"mode":"TRUMPF","trumpfColor":"DIAMONDS"}},{"broadcast":true,"messageType":"BROADCAST_GAMESTATE","data":{"version":"V0.2","trump":0,"dealer":1,"currentPlayer":0,"playerView":0,"forehand":1,"tricks":[],"player":[{"hand":["SJ","HK","DJ","H9","DQ","CQ","D8","C10","D7"]},{"hand":[]},{"hand":[]},{"hand":[]}],"jassTyp":"SCHIEBER","gameId":0}},{"broadcast":true,"messageType":"BROADCAST_GAMESTATE","data":{"version":"V0.2","trump":0,"dealer":1,"currentPlayer":0,"playerView":0,"forehand":1,"tricks":[{"first":0}],"player":[{"hand":["SJ","HK","DJ","H9","DQ","CQ","D8","C10","D7"]},{"hand":[]},{"hand":[]},{"hand":[]}],"jassTyp":"SCHIEBER","gameId":0}},{"broadcast":false,"sentTo":"roman#0","messageType":"REQUEST_CARD","data":[]},{"broadcast":false,"receivedFrom":"roman#0","messageType":"CHOOSE_CARD","data":{"number":11,"color":"DIAMONDS"}},{"broadcast":true,"messageType":"BROADCAST_GAMESTATE","data":{"version":"V0.2","trump":0,"dealer":1,"currentPlayer":3,"playerView":3,"forehand":1,"tricks":[{"first":0}],"player":[{"hand":[]},{"hand":[]},{"hand":[]},{"hand":["SA","C7","S7","C6","CK","DA","C9","DK","CJ"]}],"jassTyp":"SCHIEBER","gameId":0}},{"broadcast":true,"messageType":"PLAYED_CARDS","data":[{"number":11,"color":"DIAMONDS"}]},{"broadcast":true,"messageType":"BROADCAST_GAMESTATE","data":{"version":"V0.2","trump":0,"dealer":1,"currentPlayer":3,"playerView":3,"forehand":1,"tricks":[{"cards":["DJ"],"first":0}],"player":[{"hand":[]},{"hand":[]},{"hand":[]},{"hand":["SA","C7","S7","C6","CK","DA","C9","DK","CJ"]}],"jassTyp":"SCHIEBER","gameId":0}},{"broadcast":false,"sentTo":"Computer#1","messageType":"REQUEST_CARD","data":[{"number":11,"color":"DIAMONDS"}]},{"broadcast":false,"receivedFrom":"Computer#1","messageType":"CHOOSE_CARD","data":{"number":13,"color":"DIAMONDS"}},{"broadcast":true,"messageType":"BROADCAST_GAMESTATE","data":{"version":"V0.2","trump":0,"dealer":1,"currentPlayer":2,"playerView":2,"forehand":1,"tricks":[{"cards":["DJ"],"first":0}],"player":[{"hand":[]},{"hand":[]},{"hand":["S10","H6","D10","D9","H7","D6","HA","S9","H10"]},{"hand":[]}],"jassTyp":"SCHIEBER","gameId":0}},{"broadcast":true,"messageType":"PLAYED_CARDS","data":[{"number":11,"color":"DIAMONDS"},{"number":13,"color":"DIAMONDS"}]},{"broadcast":true,"messageType":"BROADCAST_GAMESTATE","data":{"version":"V0.2","trump":0,"dealer":1,"currentPlayer":2,"playerView":2,"forehand":1,"tricks":[{"cards":["DJ","DK"],"first":0}],"player":[{"hand":[]},{"hand":[]},{"hand":["S10","H6","D10","D9","H7","D6","HA","S9","H10"]},{"hand":[]}],"jassTyp":"SCHIEBER","gameId":0}},{"broadcast":false,"sentTo":"Computer#2","messageType":"REQUEST_CARD","data":[{"number":11,"color":"DIAMONDS"},{"number":13,"color":"DIAMONDS"}]},{"broadcast":false,"receivedFrom":"Computer#2","messageType":"CHOOSE_CARD","data":{"number":10,"color":"DIAMONDS"}},{"broadcast":true,"messageType":"BROADCAST_GAMESTATE","data":{"version":"V0.2","trump":0,"dealer":1,"currentPlayer":1,"playerView":1,"forehand":1,"tricks":[{"cards":["DJ","DK"],"first":0}],"player":[{"hand":[]},{"hand":["CA","HQ","S8","SQ","HJ","S6","H8","SK","C8"]},{"hand":[]},{"hand":[]}],"jassTyp":"SCHIEBER","gameId":0}},{"broadcast":true,"messageType":"PLAYED_CARDS","data":[{"number":11,"color":"DIAMONDS"},{"number":13,"color":"DIAMONDS"},{"number":10,"color":"DIAMONDS"}]},{"broadcast":true,"messageType":"BROADCAST_GAMESTATE","data":{"version":"V0.2","trump":0,"dealer":1,"currentPlayer":1,"playerView":1,"forehand":1,"tricks":[{"cards":["DJ","DK","D10"],"first":0}],"player":[{"hand":[]},{"hand":["CA","HQ","S8","SQ","HJ","S6","H8","SK","C8"]},{"hand":[]},{"hand":[]}],"jassTyp":"SCHIEBER","gameId":0}},{"broadcast":false,"sentTo":"Computer#3","messageType":"REQUEST_CARD","data":[{"number":11,"color":"DIAMONDS"},{"number":13,"color":"DIAMONDS"},{"number":10,"color":"DIAMONDS"}]},{"broadcast":false,"receivedFrom":"Computer#3","messageType":"CHOOSE_CARD","data":{"number":6,"color":"SPADES"}},{"broadcast":true,"messageType":"BROADCAST_GAMESTATE","data":{"version":"V0.2","trump":0,"dealer":1,"currentPlayer":0,"playerView":0,"forehand":1,"tricks":[{"cards":["DJ","DK","D10"],"first":0}],"player":[{"hand":["SJ","HK","H9","DQ","CQ","D8","C10","D7"]},{"hand":[]},{"hand":[]},{"hand":[]}],"jassTyp":"SCHIEBER","gameId":0}},{"broadcast":true,"messageType":"PLAYED_CARDS","data":[{"number":11,"color":"DIAMONDS"},{"number":13,"color":"DIAMONDS"},{"number":10,"color":"DIAMONDS"},{"number":6,"color":"SPADES"}]},{"broadcast":true,"messageType":"BROADCAST_GAMESTATE","data":{"version":"V0.2","trump":0,"dealer":1,"currentPlayer":0,"playerView":0,"forehand":1,"tricks":[{"cards":["DJ","DK","D10","S6"],"first":0}],"player":[{"hand":["SJ","HK","H9","DQ","CQ","D8","C10","D7"]},{"hand":[]},{"hand":[]},{"hand":[]}],"jassTyp":"SCHIEBER","gameId":0}},{"broadcast":true,"messageType":"BROADCAST_GAMESTATE","data":{"version":"V0.2","trump":0,"dealer":1,"currentPlayer":0,"playerView":0,"forehand":1,"tricks":[{"cards":["DJ","DK","D10","S6"],"points":34,"first":0}],"player":[{"hand":["SJ","HK","H9","DQ","CQ","D8","C10","D7"]},{"hand":[]},{"hand":[]},{"hand":[]}],"jassTyp":"SCHIEBER","gameId":0}},{"broadcast":true,"messageType":"BROADCAST_STICH","data":{"name":"roman","id":"5f81f8c3-d456-4ce6-a094-1bf83f8909b8","seatId":0,"playedCards":[{"number":11,"color":"DIAMONDS"},{"number":13,"color":"DIAMONDS"},{"number":10,"color":"DIAMONDS"},{"number":6,"color":"SPADES"}],"teams":[{"name":"Team 1","points":34,"currentRoundPoints":34,"myRound":1},{"name":"Team 2","points":0,"currentRoundPoints":0,"myRound":1}]}},{"broadcast":true,"messageType":"BROADCAST_GAMESTATE","data":{"version":"V0.2","trump":0,"dealer":1,"currentPlayer":0,"playerView":0,"forehand":1,"tricks":[{"cards":["DJ","DK","D10","S6"],"points":34,"win":0,"first":0}],"player":[{"hand":["SJ","HK","H9","DQ","CQ","D8","C10","D7"]},{"hand":[]},{"hand":[]},{"hand":[]}],"jassTyp":"SCHIEBER","gameId":0}},{"broadcast":true,"messageType":"BROADCAST_GAMESTATE","data":{"version":"V0.2","trump":0,"dealer":1,"currentPlayer":0,"playerView":0,"forehand":1,"tricks":[{"cards":["DJ","DK","D10","S6"],"points":34,"win":0,"first":0},{"first":0}],"player":[{"hand":["SJ","HK","H9","DQ","CQ","D8","C10","D7"]},{"hand":[]},{"hand":[]},{"hand":[]}],"jassTyp":"SCHIEBER","gameId":0}},{"broadcast":false,"sentTo":"roman#0","messageType":"REQUEST_CARD","data":[]},{"broadcast":false,"receivedFrom":"roman#0","messageType":"CHOOSE_CARD","data":{"number":12,"color":"DIAMONDS"}},{"broadcast":true,"messageType":"BROADCAST_GAMESTATE","data":{"version":"V0.2","trump":0,"dealer":1,"currentPlayer":3,"playerView":3,"forehand":1,"tricks":[{"cards":["DJ","DK","D10","S6"],"points":34,"win":0,"first":0},{"first":0}],"player":[{"hand":[]},{"hand":[]},{"hand":[]},{"hand":["SA","C7","S7","C6","CK","DA","C9","CJ"]}],"jassTyp":"SCHIEBER","gameId":0}},{"broadcast":true,"messageType":"PLAYED_CARDS","data":[{"number":12,"color":"DIAMONDS"}]},{"broadcast":true,"messageType":"BROADCAST_GAMESTATE","data":{"version":"V0.2","trump":0,"dealer":1,"currentPlayer":3,"playerView":3,"forehand":1,"tricks":[{"cards":["DJ","DK","D10","S6"],"points":34,"win":0,"first":0},{"cards":["DQ"],"first":0}],"player":[{"hand":[]},{"hand":[]},{"hand":[]},{"hand":["SA","C7","S7","C6","CK","DA","C9","CJ"]}],"jassTyp":"SCHIEBER","gameId":0}},{"broadcast":false,"sentTo":"Computer#1","messageType":"REQUEST_CARD","data":[{"number":12,"color":"DIAMONDS"}]},{"broadcast":false,"receivedFrom":"Computer#1","messageType":"CHOOSE_CARD","data":{"number":14,"color":"DIAMONDS"}},{"broadcast":true,"messageType":"BROADCAST_GAMESTATE","data":{"version":"V0.2","trump":0,"dealer":1,"currentPlayer":2,"playerView":2,"forehand":1,"tricks":[{"cards":["DJ","DK","D10","S6"],"points":34,"win":0,"first":0},{"cards":["DQ"],"first":0}],"player":[{"hand":[]},{"hand":[]},{"hand":["S10","H6","D9","H7","D6","HA","S9","H10"]},{"hand":[]}],"jassTyp":"SCHIEBER","gameId":0}},{"broadcast":true,"messageType":"PLAYED_CARDS","data":[{"number":12,"color":"DIAMONDS"},{"number":14,"color":"DIAMONDS"}]},{"broadcast":true,"messageType":"BROADCAST_GAMESTATE","data":{"version":"V0.2","trump":0,"dealer":1,"currentPlayer":2,"playerView":2,"forehand":1,"tricks":[{"cards":["DJ","DK","D10","S6"],"points":34,"win":0,"first":0},{"cards":["DQ","DA"],"first":0}],"player":[{"hand":[]},{"hand":[]},{"hand":["S10","H6","D9","H7","D6","HA","S9","H10"]},{"hand":[]}],"jassTyp":"SCHIEBER","gameId":0}},{"broadcast":false,"sentTo":"Computer#2","messageType":"REQUEST_CARD","data":[{"number":12,"color":"DIAMONDS"},{"number":14,"color":"DIAMONDS"}]},{"broadcast":false,"receivedFrom":"Computer#2","messageType":"CHOOSE_CARD","data":{"number":9,"color":"DIAMONDS"}},{"broadcast":true,"messageType":"BROADCAST_GAMESTATE","data":{"version":"V0.2","trump":0,"dealer":1,"currentPlayer":1,"playerView":1,"forehand":1,"tricks":[{"cards":["DJ","DK","D10","S6"],"points":34,"win":0,"first":0},{"cards":["DQ","DA"],"first":0}],"player":[{"hand":[]},{"hand":["CA","HQ","S8","SQ","HJ","H8","SK","C8"]},{"hand":[]},{"hand":[]}],"jassTyp":"SCHIEBER","gameId":0}},{"broadcast":true,"messageType":"PLAYED_CARDS","data":[{"number":12,"color":"DIAMONDS"},{"number":14,"color":"DIAMONDS"},{"number":9,"color":"DIAMONDS"}]},{"broadcast":true,"messageType":"BROADCAST_GAMESTATE","data":{"version":"V0.2","trump":0,"dealer":1,"currentPlayer":1,"playerView":1,"forehand":1,"tricks":[{"cards":["DJ","DK","D10","S6"],"points":34,"win":0,"first":0},{"cards":["DQ","DA","D9"],"first":0}],"player":[{"hand":[]},{"hand":["CA","HQ","S8","SQ","HJ","H8","SK","C8"]},{"hand":[]},{"hand":[]}],"jassTyp":"SCHIEBER","gameId":0}},{"broadcast":false,"sentTo":"Computer#3","messageType":"REQUEST_CARD","data":[{"number":12,"color":"DIAMONDS"},{"number":14,"color":"DIAMONDS"},{"number":9,"color":"DIAMONDS"}]},{"broadcast":false,"receivedFrom":"Computer#3","messageType":"CHOOSE_CARD","data":{"number":8,"color":"SPADES"}},{"broadcast":true,"messageType":"BROADCAST_GAMESTATE","data":{"version":"V0.2","trump":0,"dealer":1,"currentPlayer":0,"playerView":0,"forehand":1,"tricks":[{"cards":["DJ","DK","D10","S6"],"points":34,"win":0,"first":0},{"cards":["DQ","DA","D9"],"first":0}],"player":[{"hand":["SJ","HK","H9","CQ","D8","C10","D7"]},{"hand":[]},{"hand":[]},{"hand":[]}],"jassTyp":"SCHIEBER","gameId":0}},{"broadcast":true,"messageType":"PLAYED_CARDS","data":[{"number":12,"color":"DIAMONDS"},{"number":14,"color":"DIAMONDS"},{"number":9,"color":"DIAMONDS"},{"number":8,"color":"SPADES"}]},{"broadcast":true,"messageType":"BROADCAST_GAMESTATE","data":{"version":"V0.2","trump":0,"dealer":1,"currentPlayer":0,"playerView":0,"forehand":1,"tricks":[{"cards":["DJ","DK","D10","S6"],"points":34,"win":0,"first":0},{"cards":["DQ","DA","D9","S8"],"first":0}],"player":[{"hand":["SJ","HK","H9","CQ","D8","C10","D7"]},{"hand":[]},{"hand":[]},{"hand":[]}],"jassTyp":"SCHIEBER","gameId":0}},{"broadcast":true,"messageType":"BROADCAST_GAMESTATE","data":{"version":"V0.2","trump":0,"dealer":1,"currentPlayer":0,"playerView":0,"forehand":1,"tricks":[{"cards":["DJ","DK","D10","S6"],"points":34,"win":0,"first":0},{"cards":["DQ","DA","D9","S8"],"points":28,"first":0}],"player":[{"hand":["SJ","HK","H9","CQ","D8","C10","D7"]},{"hand":[]},{"hand":[]},{"hand":[]}],"jassTyp":"SCHIEBER","gameId":0}},{"broadcast":true,"messageType":"BROADCAST_STICH","data":{"name":"Computer","id":"d0705f78-4713-41e8-a54b-d242d3f63a0e","seatId":2,"playedCards":[{"number":12,"color":"DIAMONDS"},{"number":14,"color":"DIAMONDS"},{"number":9,"color":"DIAMONDS"},{"number":8,"color":"SPADES"}],"teams":[{"name":"Team 1","points":62,"currentRoundPoints":62,"myRound":1},{"name":"Team 2","points":0,"currentRoundPoints":0,"myRound":1}]}},{"broadcast":true,"messageType":"BROADCAST_GAMESTATE","data":{"version":"V0.2","trump":0,"dealer":1,"currentPlayer":0,"playerView":0,"forehand":1,"tricks":[{"cards":["DJ","DK","D10","S6"],"points":34,"win":0,"first":0},{"cards":["DQ","DA","D9","S8"],"points":28,"win":2,"first":0}],"player":[{"hand":["SJ","HK","H9","CQ","D8","C10","D7"]},{"hand":[]},{"hand":[]},{"hand":[]}],"jassTyp":"SCHIEBER","gameId":0}},{"broadcast":true,"messageType":"BROADCAST_GAMESTATE","data":{"version":"V0.2","trump":0,"dealer":1,"currentPlayer":2,"playerView":2,"forehand":1,"tricks":[{"cards":["DJ","DK","D10","S6"],"points":34,"win":0,"first":0},{"cards":["DQ","DA","D9","S8"],"points":28,"win":2,"first":0},{"first":2}],"player":[{"hand":[]},{"hand":[]},{"hand":["S10","H6","H7","D6","HA","S9","H10"]},{"hand":[]}],"jassTyp":"SCHIEBER","gameId":0}},{"broadcast":false,"sentTo":"Computer#2","messageType":"REQUEST_CARD","data":[]},{"broadcast":false,"receivedFrom":"Computer#2","messageType":"CHOOSE_CARD","data":{"number":14,"color":"HEARTS"}},{"broadcast":true,"messageType":"BROADCAST_GAMESTATE","data":{"version":"V0.2","trump":0,"dealer":1,"currentPlayer":1,"playerView":1,"forehand":1,"tricks":[{"cards":["DJ","DK","D10","S6"],"points":34,"win":0,"first":0},{"cards":["DQ","DA","D9","S8"],"points":28,"win":2,"first":0},{"first":2}],"player":[{"hand":[]},{"hand":["CA","HQ","SQ","HJ","H8","SK","C8"]},{"hand":[]},{"hand":[]}],"jassTyp":"SCHIEBER","gameId":0}},{"broadcast":true,"messageType":"PLAYED_CARDS","data":[{"number":14,"color":"HEARTS"}]},{"broadcast":true,"messageType":"BROADCAST_GAMESTATE","data":{"version":"V0.2","trump":0,"dealer":1,"currentPlayer":1,"playerView":1,"forehand":1,"tricks":[{"cards":["DJ","DK","D10","S6"],"points":34,"win":0,"first":0},{"cards":["DQ","DA","D9","S8"],"points":28,"win":2,"first":0},{"cards":["HA"],"first":2}],"player":[{"hand":[]},{"hand":["CA","HQ","SQ","HJ","H8","SK","C8"]},{"hand":[]},{"hand":[]}],"jassTyp":"SCHIEBER","gameId":0}},{"broadcast":false,"sentTo":"Computer#3","messageType":"REQUEST_CARD","data":[{"number":14,"color":"HEARTS"}]},{"broadcast":false,"receivedFrom":"Computer#3","messageType":"CHOOSE_CARD","data":{"number":8,"color":"HEARTS"}},{"broadcast":true,"messageType":"BROADCAST_GAMESTATE","data":{"version":"V0.2","trump":0,"dealer":1,"currentPlayer":0,"playerView":0,"forehand":1,"tricks":[{"cards":["DJ","DK","D10","S6"],"points":34,"win":0,"first":0},{"cards":["DQ","DA","D9","S8"],"points":28,"win":2,"first":0},{"cards":["HA"],"first":2}],"player":[{"hand":["SJ","HK","H9","CQ","D8","C10","D7"]},{"hand":[]},{"hand":[]},{"hand":[]}],"jassTyp":"SCHIEBER","gameId":0}},{"broadcast":true,"messageType":"PLAYED_CARDS","data":[{"number":14,"color":"HEARTS"},{"number":8,"color":"HEARTS"}]},{"broadcast":true,"messageType":"BROADCAST_GAMESTATE","data":{"version":"V0.2","trump":0,"dealer":1,"currentPlayer":0,"playerView":0,"forehand":1,"tricks":[{"cards":["DJ","DK","D10","S6"],"points":34,"win":0,"first":0},{"cards":["DQ","DA","D9","S8"],"points":28,"win":2,"first":0},{"cards":["HA","H8"],"first":2}],"player":[{"hand":["SJ","HK","H9","CQ","D8","C10","D7"]},{"hand":[]},{"hand":[]},{"hand":[]}],"jassTyp":"SCHIEBER","gameId":0}},{"broadcast":false,"sentTo":"roman#0","messageType":"REQUEST_CARD","data":[{"number":14,"color":"HEARTS"},{"number":8,"color":"HEARTS"}]},{"broadcast":false,"receivedFrom":"roman#0","messageType":"CHOOSE_CARD","data":{"number":8,"color":"DIAMONDS"}},{"broadcast":true,"messageType":"BROADCAST_GAMESTATE","data":{"version":"V0.2","trump":0,"dealer":1,"currentPlayer":3,"playerView":3,"forehand":1,"tricks":[{"cards":["DJ","DK","D10","S6"],"points":34,"win":0,"first":0},{"cards":["DQ","DA","D9","S8"],"points":28,"win":2,"first":0},{"cards":["HA","H8"],"first":2}],"player":[{"hand":[]},{"hand":[]},{"hand":[]},{"hand":["SA","C7","S7","C6","CK","C9","CJ"]}],"jassTyp":"SCHIEBER","gameId":0}},{"broadcast":true,"messageType":"PLAYED_CARDS","data":[{"number":14,"color":"HEARTS"},{"number":8,"color":"HEARTS"},{"number":8,"color":"DIAMONDS"}]},{"broadcast":true,"messageType":"BROADCAST_GAMESTATE","data":{"version":"V0.2","trump":0,"dealer":1,"currentPlayer":3,"playerView":3,"forehand":1,"tricks":[{"cards":["DJ","DK","D10","S6"],"points":34,"win":0,"first":0},{"cards":["DQ","DA","D9","S8"],"points":28,"win":2,"first":0},{"cards":["HA","H8","D8"],"first":2}],"player":[{"hand":[]},{"hand":[]},{"hand":[]},{"hand":["SA","C7","S7","C6","CK","C9","CJ"]}],"jassTyp":"SCHIEBER","gameId":0}},{"broadcast":false,"sentTo":"Computer#1","messageType":"REQUEST_CARD","data":[{"number":14,"color":"HEARTS"},{"number":8,"color":"HEARTS"},{"number":8,"color":"DIAMONDS"}]},{"broadcast":false,"receivedFrom":"Computer#1","messageType":"CHOOSE_CARD","data":{"number":7,"color":"SPADES"}},{"broadcast":true,"messageType":"BROADCAST_GAMESTATE","data":{"version":"V0.2","trump":0,"dealer":1,"currentPlayer":2,"playerView":2,"forehand":1,"tricks":[{"cards":["DJ","DK","D10","S6"],"points":34,"win":0,"first":0},{"cards":["DQ","DA","D9","S8"],"points":28,"win":2,"first":0},{"cards":["HA","H8","D8"],"first":2}],"player":[{"hand":[]},{"hand":[]},{"hand":["S10","H6","H7","D6","S9","H10"]},{"hand":[]}],"jassTyp":"SCHIEBER","gameId":0}},{"broadcast":true,"messageType":"PLAYED_CARDS","data":[{"number":14,"color":"HEARTS"},{"number":8,"color":"HEARTS"},{"number":8,"color":"DIAMONDS"},{"number":7,"color":"SPADES"}]},{"broadcast":true,"messageType":"BROADCAST_GAMESTATE","data":{"version":"V0.2","trump":0,"dealer":1,"currentPlayer":2,"playerView":2,"forehand":1,"tricks":[{"cards":["DJ","DK","D10","S6"],"points":34,"win":0,"first":0},{"cards":["DQ","DA","D9","S8"],"points":28,"win":2,"first":0},{"cards":["HA","H8","D8","S7"],"first":2}],"player":[{"hand":[]},{"hand":[]},{"hand":["S10","H6","H7","D6","S9","H10"]},{"hand":[]}],"jassTyp":"SCHIEBER","gameId":0}},{"broadcast":true,"messageType":"BROADCAST_GAMESTATE","data":{"version":"V0.2","trump":0,"dealer":1,"currentPlayer":2,"playerView":2,"forehand":1,"tricks":[{"cards":["DJ","DK","D10","S6"],"points":34,"win":0,"first":0},{"cards":["DQ","DA","D9","S8"],"points":28,"win":2,"first":0},{"cards":["HA","H8","D8","S7"],"points":11,"first":2}],"player":[{"hand":[]},{"hand":[]},{"hand":["S10","H6","H7","D6","S9","H10"]},{"hand":[]}],"jassTyp":"SCHIEBER","gameId":0}},{"broadcast":true,"messageType":"BROADCAST_STICH","data":{"name":"roman","id":"5f81f8c3-d456-4ce6-a094-1bf83f8909b8","seatId":0,"playedCards":[{"number":14,"color":"HEARTS"},{"number":8,"color":"HEARTS"},{"number":8,"color":"DIAMONDS"},{"number":7,"color":"SPADES"}],"teams":[{"name":"Team 1","points":73,"currentRoundPoints":73,"myRound":1},{"name":"Team 2","points":0,"currentRoundPoints":0,"myRound":1}]}},{"broadcast":true,"messageType":"BROADCAST_GAMESTATE","data":{"version":"V0.2","trump":0,"dealer":1,"currentPlayer":2,"playerView":2,"forehand":1,"tricks":[{"cards":["DJ","DK","D10","S6"],"points":34,"win":0,"first":0},{"cards":["DQ","DA","D9","S8"],"points":28,"win":2,"first":0},{"cards":["HA","H8","D8","S7"],"points":11,"win":0,"first":2}],"player":[{"hand":[]},{"hand":[]},{"hand":["S10","H6","H7","D6","S9","H10"]},{"hand":[]}],"jassTyp":"SCHIEBER","gameId":0}},{"broadcast":true,"messageType":"BROADCAST_GAMESTATE","data":{"version":"V0.2","trump":0,"dealer":1,"currentPlayer":0,"playerView":0,"forehand":1,"tricks":[{"cards":["DJ","DK","D10","S6"],"points":34,"win":0,"first":0},{"cards":["DQ","DA","D9","S8"],"points":28,"win":2,"first":0},{"cards":["HA","H8","D8","S7"],"points":11,"win":0,"first":2},{"first":0}],"player":[{"hand":["SJ","HK","H9","CQ","C10","D7"]},{"hand":[]},{"hand":[]},{"hand":[]}],"jassTyp":"SCHIEBER","gameId":0}},{"broadcast":false,"sentTo":"roman#0","messageType":"REQUEST_CARD","data":[]},{"broadcast":false,"receivedFrom":"roman#0","messageType":"CHOOSE_CARD","data":{"number":7,"color":"DIAMONDS"}},{"broadcast":true,"messageType":"BROADCAST_GAMESTATE","data":{"version":"V0.2","trump":0,"dealer":1,"currentPlayer":3,"playerView":3,"forehand":1,"tricks":[{"cards":["DJ","DK","D10","S6"],"points":34,"win":0,"first":0},{"cards":["DQ","DA","D9","S8"],"points":28,"win":2,"first":0},{"cards":["HA","H8","D8","S7"],"points":11,"win":0,"first":2},{"first":0}],"player":[{"hand":[]},{"hand":[]},{"hand":[]},{"hand":["SA","C7","C6","CK","C9","CJ"]}],"jassTyp":"SCHIEBER","gameId":0}},{"broadcast":true,"messageType":"PLAYED_CARDS","data":[{"number":7,"color":"DIAMONDS"}]},{"broadcast":true,"messageType":"BROADCAST_GAMESTATE","data":{"version":"V0.2","trump":0,"dealer":1,"currentPlayer":3,"playerView":3,"forehand":1,"tricks":[{"cards":["DJ","DK","D10","S6"],"points":34,"win":0,"first":0},{"cards":["DQ","DA","D9","S8"],"points":28,"win":2,"first":0},{"cards":["HA","H8","D8","S7"],"points":11,"win":0,"first":2},{"cards":["D7"],"first":0}],"player":[{"hand":[]},{"hand":[]},{"hand":[]},{"hand":["SA","C7","C6","CK","C9","CJ"]}],"jassTyp":"SCHIEBER","gameId":0}},{"broadcast":false,"sentTo":"Computer#1","messageType":"REQUEST_CARD","data":[{"number":7,"color":"DIAMONDS"}]},{"broadcast":false,"receivedFrom":"Computer#1","messageType":"CHOOSE_CARD","data":{"number":7,"color":"CLUBS"}},{"broadcast":true,"messageType":"BROADCAST_GAMESTATE","data":{"version":"V0.2","trump":0,"dealer":1,"currentPlayer":2,"playerView":2,"forehand":1,"tricks":[{"cards":["DJ","DK","D10","S6"],"points":34,"win":0,"first":0},{"cards":["DQ","DA","D9","S8"],"points":28,"win":2,"first":0},{"cards":["HA","H8","D8","S7"],"points":11,"win":0,"first":2},{"cards":["D7"],"first":0}],"player":[{"hand":[]},{"hand":[]},{"hand":["S10","H6","H7","D6","S9","H10"]},{"hand":[]}],"jassTyp":"SCHIEBER","gameId":0}},{"broadcast":true,"messageType":"PLAYED_CARDS","data":[{"number":7,"color":"DIAMONDS"},{"number":7,"color":"CLUBS"}]},{"broadcast":true,"messageType":"BROADCAST_GAMESTATE","data":{"version":"V0.2","trump":0,"dealer":1,"currentPlayer":2,"playerView":2,"forehand":1,"tricks":[{"cards":["DJ","DK","D10","S6"],"points":34,"win":0,"first":0},{"cards":["DQ","DA","D9","S8"],"points":28,"win":2,"first":0},{"cards":["HA","H8","D8","S7"],"points":11,"win":0,"first":2},{"cards":["D7","C7"],"first":0}],"player":[{"hand":[]},{"hand":[]},{"hand":["S10","H6","H7","D6","S9","H10"]},{"hand":[]}],"jassTyp":"SCHIEBER","gameId":0}},{"broadcast":false,"sentTo":"Computer#2","messageType":"REQUEST_CARD","data":[{"number":7,"color":"DIAMONDS"},{"number":7,"color":"CLUBS"}]},{"broadcast":false,"receivedFrom":"Computer#2","messageType":"CHOOSE_CARD","data":{"number":6,"color":"DIAMONDS"}},{"broadcast":true,"messageType":"BROADCAST_GAMESTATE","data":{"version":"V0.2","trump":0,"dealer":1,"currentPlayer":1,"playerView":1,"forehand":1,"tricks":[{"cards":["DJ","DK","D10","S6"],"points":34,"win":0,"first":0},{"cards":["DQ","DA","D9","S8"],"points":28,"win":2,"first":0},{"cards":["HA","H8","D8","S7"],"points":11,"win":0,"first":2},{"cards":["D7","C7"],"first":0}],"player":[{"hand":[]},{"hand":["CA","HQ","SQ","HJ","SK","C8"]},{"hand":[]},{"hand":[]}],"jassTyp":"SCHIEBER","gameId":0}},{"broadcast":true,"messageType":"PLAYED_CARDS","data":[{"number":7,"color":"DIAMONDS"},{"number":7,"color":"CLUBS"},{"number":6,"color":"DIAMONDS"}]},{"broadcast":true,"messageType":"BROADCAST_GAMESTATE","data":{"version":"V0.2","trump":0,"dealer":1,"currentPlayer":1,"playerView":1,"forehand":1,"tricks":[{"cards":["DJ","DK","D10","S6"],"points":34,"win":0,"first":0},{"cards":["DQ","DA","D9","S8"],"points":28,"win":2,"first":0},{"cards":["HA","H8","D8","S7"],"points":11,"win":0,"first":2},{"cards":["D7","C7","D6"],"first":0}],"player":[{"hand":[]},{"hand":["CA","HQ","SQ","HJ","SK","C8"]},{"hand":[]},{"hand":[]}],"jassTyp":"SCHIEBER","gameId":0}},{"broadcast":false,"sentTo":"Computer#3","messageType":"REQUEST_CARD","data":[{"number":7,"color":"DIAMONDS"},{"number":7,"color":"CLUBS"},{"number":6,"color":"DIAMONDS"}]},{"broadcast":false,"receivedFrom":"Computer#3","messageType":"CHOOSE_CARD","data":{"number":8,"color":"CLUBS"}},{"broadcast":true,"messageType":"BROADCAST_GAMESTATE","data":{"version":"V0.2","trump":0,"dealer":1,"currentPlayer":0,"playerView":0,"forehand":1,"tricks":[{"cards":["DJ","DK","D10","S6"],"points":34,"win":0,"first":0},{"cards":["DQ","DA","D9","S8"],"points":28,"win":2,"first":0},{"cards":["HA","H8","D8","S7"],"points":11,"win":0,"first":2},{"cards":["D7","C7","D6"],"first":0}],"player":[{"hand":["SJ","HK","H9","CQ","C10"]},{"hand":[]},{"hand":[]},{"hand":[]}],"jassTyp":"SCHIEBER","gameId":0}},{"broadcast":true,"messageType":"PLAYED_CARDS","data":[{"number":7,"color":"DIAMONDS"},{"number":7,"color":"CLUBS"},{"number":6,"color":"DIAMONDS"},{"number":8,"color":"CLUBS"}]},{"broadcast":true,"messageType":"BROADCAST_GAMESTATE","data":{"version":"V0.2","trump":0,"dealer":1,"currentPlayer":0,"playerView":0,"forehand":1,"tricks":[{"cards":["DJ","DK","D10","S6"],"points":34,"win":0,"first":0},{"cards":["DQ","DA","D9","S8"],"points":28,"win":2,"first":0},{"cards":["HA","H8","D8","S7"],"points":11,"win":0,"first":2},{"cards":["D7","C7","D6","C8"],"first":0}],"player":[{"hand":["SJ","HK","H9","CQ","C10"]},{"hand":[]},{"hand":[]},{"hand":[]}],"jassTyp":"SCHIEBER","gameId":0}},{"broadcast":true,"messageType":"BROADCAST_GAMESTATE","data":{"version":"V0.2","trump":0,"dealer":1,"currentPlayer":0,"playerView":0,"forehand":1,"tricks":[{"cards":["DJ","DK","D10","S6"],"points":34,"win":0,"first":0},{"cards":["DQ","DA","D9","S8"],"points":28,"win":2,"first":0},{"cards":["HA","H8","D8","S7"],"points":11,"win":0,"first":2},{"cards":["D7","C7","D6","C8"],"points":0,"first":0}],"player":[{"hand":["SJ","HK","H9","CQ","C10"]},{"hand":[]},{"hand":[]},{"hand":[]}],"jassTyp":"SCHIEBER","gameId":0}},{"broadcast":true,"messageType":"BROADCAST_STICH","data":{"name":"roman","id":"5f81f8c3-d456-4ce6-a094-1bf83f8909b8","seatId":0,"playedCards":[{"number":7,"color":"DIAMONDS"},{"number":7,"color":"CLUBS"},{"number":6,"color":"DIAMONDS"},{"number":8,"color":"CLUBS"}],"teams":[{"name":"Team 1","points":73,"currentRoundPoints":73,"myRound":1},{"name":"Team 2","points":0,"currentRoundPoints":0,"myRound":1}]}},{"broadcast":true,"messageType":"BROADCAST_GAMESTATE","data":{"version":"V0.2","trump":0,"dealer":1,"currentPlayer":0,"playerView":0,"forehand":1,"tricks":[{"cards":["DJ","DK","D10","S6"],"points":34,"win":0,"first":0},{"cards":["DQ","DA","D9","S8"],"points":28,"win":2,"first":0},{"cards":["HA","H8","D8","S7"],"points":11,"win":0,"first":2},{"cards":["D7","C7","D6","C8"],"points":0,"win":0,"first":0}],"player":[{"hand":["SJ","HK","H9","CQ","C10"]},{"hand":[]},{"hand":[]},{"hand":[]}],"jassTyp":"SCHIEBER","gameId":0}},{"broadcast":true,"messageType":"BROADCAST_GAMESTATE","data":{"version":"V0.2","trump":0,"dealer":1,"currentPlayer":0,"playerView":0,"forehand":1,"tricks":[{"cards":["DJ","DK","D10","S6"],"points":34,"win":0,"first":0},{"cards":["DQ","DA","D9","S8"],"points":28,"win":2,"first":0},{"cards":["HA","H8","D8","S7"],"points":11,"win":0,"first":2},{"cards":["D7","C7","D6","C8"],"points":0,"win":0,"first":0},{"first":0}],"player":[{"hand":["SJ","HK","H9","CQ","C10"]},{"hand":[]},{"hand":[]},{"hand":[]}],"jassTyp":"SCHIEBER","gameId":0}},{"broadcast":false,"sentTo":"roman#0","messageType":"REQUEST_CARD","data":[]},{"broadcast":false,"receivedFrom":"roman#0","messageType":"CHOOSE_CARD","data":{"number":11,"color":"SPADES"}},{"broadcast":true,"messageType":"BROADCAST_GAMESTATE","data":{"version":"V0.2","trump":0,"dealer":1,"currentPlayer":3,"playerView":3,"forehand":1,"tricks":[{"cards":["DJ","DK","D10","S6"],"points":34,"win":0,"first":0},{"cards":["DQ","DA","D9","S8"],"points":28,"win":2,"first":0},{"cards":["HA","H8","D8","S7"],"points":11,"win":0,"first":2},{"cards":["D7","C7","D6","C8"],"points":0,"win":0,"first":0},{"first":0}],"player":[{"hand":[]},{"hand":[]},{"hand":[]},{"hand":["SA","C6","CK","C9","CJ"]}],"jassTyp":"SCHIEBER","gameId":0}},{"broadcast":true,"messageType":"PLAYED_CARDS","data":[{"number":11,"color":"SPADES"}]},{"broadcast":true,"messageType":"BROADCAST_GAMESTATE","data":{"version":"V0.2","trump":0,"dealer":1,"currentPlayer":3,"playerView":3,"forehand":1,"tricks":[{"cards":["DJ","DK","D10","S6"],"points":34,"win":0,"first":0},{"cards":["DQ","DA","D9","S8"],"points":28,"win":2,"first":0},{"cards":["HA","H8","D8","S7"],"points":11,"win":0,"first":2},{"cards":["D7","C7","D6","C8"],"points":0,"win":0,"first":0},{"cards":["SJ"],"first":0}],"player":[{"hand":[]},{"hand":[]},{"hand":[]},{"hand":["SA","C6","CK","C9","CJ"]}],"jassTyp":"SCHIEBER","gameId":0}},{"broadcast":false,"sentTo":"Computer#1","messageType":"REQUEST_CARD","data":[{"number":11,"color":"SPADES"}]},{"broadcast":false,"receivedFrom":"Computer#1","messageType":"CHOOSE_CARD","data":{"number":14,"color":"SPADES"}},{"broadcast":true,"messageType":"BROADCAST_GAMESTATE","data":{"version":"V0.2","trump":0,"dealer":1,"currentPlayer":2,"playerView":2,"forehand":1,"tricks":[{"cards":["DJ","DK","D10","S6"],"points":34,"win":0,"first":0},{"cards":["DQ","DA","D9","S8"],"points":28,"win":2,"first":0},{"cards":["HA","H8","D8","S7"],"points":11,"win":0,"first":2},{"cards":["D7","C7","D6","C8"],"points":0,"win":0,"first":0},{"cards":["SJ"],"first":0}],"player":[{"hand":[]},{"hand":[]},{"hand":["S10","H6","H7","S9","H10"]},{"hand":[]}],"jassTyp":"SCHIEBER","gameId":0}},{"broadcast":true,"messageType":"PLAYED_CARDS","data":[{"number":11,"color":"SPADES"},{"number":14,"color":"SPADES"}]},{"broadcast":true,"messageType":"BROADCAST_GAMESTATE","data":{"version":"V0.2","trump":0,"dealer":1,"currentPlayer":2,"playerView":2,"forehand":1,"tricks":[{"cards":["DJ","DK","D10","S6"],"points":34,"win":0,"first":0},{"cards":["DQ","DA","D9","S8"],"points":28,"win":2,"first":0},{"cards":["HA","H8","D8","S7"],"points":11,"win":0,"first":2},{"cards":["D7","C7","D6","C8"],"points":0,"win":0,"first":0},{"cards":["SJ","SA"],"first":0}],"player":[{"hand":[]},{"hand":[]},{"hand":["S10","H6","H7","S9","H10"]},{"hand":[]}],"jassTyp":"SCHIEBER","gameId":0}},{"broadcast":false,"sentTo":"Computer#2","messageType":"REQUEST_CARD","data":[{"number":11,"color":"SPADES"},{"number":14,"color":"SPADES"}]},{"broadcast":false,"receivedFrom":"Computer#2","messageType":"CHOOSE_CARD","data":{"number":9,"color":"SPADES"}},{"broadcast":true,"messageType":"BROADCAST_GAMESTATE","data":{"version":"V0.2","trump":0,"dealer":1,"currentPlayer":1,"playerView":1,"forehand":1,"tricks":[{"cards":["DJ","DK","D10","S6"],"points":34,"win":0,"first":0},{"cards":["DQ","DA","D9","S8"],"points":28,"win":2,"first":0},{"cards":["HA","H8","D8","S7"],"points":11,"win":0,"first":2},{"cards":["D7","C7","D6","C8"],"points":0,"win":0,"first":0},{"cards":["SJ","SA"],"first":0}],"player":[{"hand":[]},{"hand":["CA","HQ","SQ","HJ","SK"]},{"hand":[]},{"hand":[]}],"jassTyp":"SCHIEBER","gameId":0}},{"broadcast":true,"messageType":"PLAYED_CARDS","data":[{"number":11,"color":"SPADES"},{"number":14,"color":"SPADES"},{"number":9,"color":"SPADES"}]},{"broadcast":true,"messageType":"BROADCAST_GAMESTATE","data":{"version":"V0.2","trump":0,"dealer":1,"currentPlayer":1,"playerView":1,"forehand":1,"tricks":[{"cards":["DJ","DK","D10","S6"],"points":34,"win":0,"first":0},{"cards":["DQ","DA","D9","S8"],"points":28,"win":2,"first":0},{"cards":["HA","H8","D8","S7"],"points":11,"win":0,"first":2},{"cards":["D7","C7","D6","C8"],"points":0,"win":0,"first":0},{"cards":["SJ","SA","S9"],"first":0}],"player":[{"hand":[]},{"hand":["CA","HQ","SQ","HJ","SK"]},{"hand":[]},{"hand":[]}],"jassTyp":"SCHIEBER","gameId":0}},{"broadcast":false,"sentTo":"Computer#3","messageType":"REQUEST_CARD","data":[{"number":11,"color":"SPADES"},{"number":14,"color":"SPADES"},{"number":9,"color":"SPADES"}]},{"broadcast":false,"receivedFrom":"Computer#3","messageType":"CHOOSE_CARD","data":{"number":13,"color":"SPADES"}},{"broadcast":true,"messageType":"BROADCAST_GAMESTATE","data":{"version":"V0.2","trump":0,"dealer":1,"currentPlayer":0,"playerView":0,"forehand":1,"tricks":[{"cards":["DJ","DK","D10","S6"],"points":34,"win":0,"first":0},{"cards":["DQ","DA","D9","S8"],"points":28,"win":2,"first":0},{"cards":["HA","H8","D8","S7"],"points":11,"win":0,"first":2},{"cards":["D7","C7","D6","C8"],"points":0,"win":0,"first":0},{"cards":["SJ","SA","S9"],"first":0}],"player":[{"hand":["HK","H9","CQ","C10"]},{"hand":[]},{"hand":[]},{"hand":[]}],"jassTyp":"SCHIEBER","gameId":0}},{"broadcast":true,"messageType":"PLAYED_CARDS","data":[{"number":11,"color":"SPADES"},{"number":14,"color":"SPADES"},{"number":9,"color":"SPADES"},{"number":13,"color":"SPADES"}]},{"broadcast":true,"messageType":"BROADCAST_GAMESTATE","data":{"version":"V0.2","trump":0,"dealer":1,"currentPlayer":0,"playerView":0,"forehand":1,"tricks":[{"cards":["DJ","DK","D10","S6"],"points":34,"win":0,"first":0},{"cards":["DQ","DA","D9","S8"],"points":28,"win":2,"first":0},{"cards":["HA","H8","D8","S7"],"points":11,"win":0,"first":2},{"cards":["D7","C7","D6","C8"],"points":0,"win":0,"first":0},{"cards":["SJ","SA","S9","SK"],"first":0}],"player":[{"hand":["HK","H9","CQ","C10"]},{"hand":[]},{"hand":[]},{"hand":[]}],"jassTyp":"SCHIEBER","gameId":0}},{"broadcast":true,"messageType":"BROADCAST_GAMESTATE","data":{"version":"V0.2","trump":0,"dealer":1,"currentPlayer":0,"playerView":0,"forehand":1,"tricks":[{"cards":["DJ","DK","D10","S6"],"points":34,"win":0,"first":0},{"cards":["DQ","DA","D9","S8"],"points":28,"win":2,"first":0},{"cards":["HA","H8","D8","S7"],"points":11,"win":0,"first":2},{"cards":["D7","C7","D6","C8"],"points":0,"win":0,"first":0},{"cards":["SJ","SA","S9","SK"],"points":17,"first":0}],"player":[{"hand":["HK","H9","CQ","C10"]},{"hand":[]},{"hand":[]},{"hand":[]}],"jassTyp":"SCHIEBER","gameId":0}},{"broadcast":true,"messageType":"BROADCAST_STICH","data":{"name":"Computer","id":"6f661d6d-a8fd-48b2-b9df-8b73278fafcc","seatId":1,"playedCards":[{"number":11,"color":"SPADES"},{"number":14,"color":"SPADES"},{"number":9,"color":"SPADES"},{"number":13,"color":"SPADES"}],"teams":[{"name":"Team 2","points":17,"currentRoundPoints":17,"myRound":1},{"name":"Team 1","points":73,"currentRoundPoints":73,"myRound":1}]}},{"broadcast":true,"messageType":"BROADCAST_GAMESTATE","data":{"version":"V0.2","trump":0,"dealer":1,"currentPlayer":0,"playerView":0,"forehand":1,"tricks":[{"cards":["DJ","DK","D10","S6"],"points":34,"win":0,"first":0},{"cards":["DQ","DA","D9","S8"],"points":28,"win":2,"first":0},{"cards":["HA","H8","D8","S7"],"points":11,"win":0,"first":2},{"cards":["D7","C7","D6","C8"],"points":0,"win":0,"first":0},{"cards":["SJ","SA","S9","SK"],"points":17,"win":3,"first":0}],"player":[{"hand":["HK","H9","CQ","C10"]},{"hand":[]},{"hand":[]},{"hand":[]}],"jassTyp":"SCHIEBER","gameId":0}},{"broadcast":true,"messageType":"BROADCAST_GAMESTATE","data":{"version":"V0.2","trump":0,"dealer":1,"currentPlayer":3,"playerView":3,"forehand":1,"tricks":[{"cards":["DJ","DK","D10","S6"],"points":34,"win":0,"first":0},{"cards":["DQ","DA","D9","S8"],"points":28,"win":2,"first":0},{"cards":["HA","H8","D8","S7"],"points":11,"win":0,"first":2},{"cards":["D7","C7","D6","C8"],"points":0,"win":0,"first":0},{"cards":["SJ","SA","S9","SK"],"points":17,"win":3,"first":0},{"first":3}],"player":[{"hand":[]},{"hand":[]},{"hand":[]},{"hand":["C6","CK","C9","CJ"]}],"jassTyp":"SCHIEBER","gameId":0}},{"broadcast":false,"sentTo":"Computer#1","messageType":"REQUEST_CARD","data":[]},{"broadcast":false,"receivedFrom":"Computer#1","messageType":"CHOOSE_CARD","data":{"number":13,"color":"CLUBS"}},{"broadcast":true,"messageType":"BROADCAST_GAMESTATE","data":{"version":"V0.2","trump":0,"dealer":1,"currentPlayer":2,"playerView":2,"forehand":1,"tricks":[{"cards":["DJ","DK","D10","S6"],"points":34,"win":0,"first":0},{"cards":["DQ","DA","D9","S8"],"points":28,"win":2,"first":0},{"cards":["HA","H8","D8","S7"],"points":11,"win":0,"first":2},{"cards":["D7","C7","D6","C8"],"points":0,"win":0,"first":0},{"cards":["SJ","SA","S9","SK"],"points":17,"win":3,"first":0},{"first":3}],"player":[{"hand":[]},{"hand":[]},{"hand":["S10","H6","H7","H10"]},{"hand":[]}],"jassTyp":"SCHIEBER","gameId":0}},{"broadcast":true,"messageType":"PLAYED_CARDS","data":[{"number":13,"color":"CLUBS"}]},{"broadcast":true,"messageType":"BROADCAST_GAMESTATE","data":{"version":"V0.2","trump":0,"dealer":1,"currentPlayer":2,"playerView":2,"forehand":1,"tricks":[{"cards":["DJ","DK","D10","S6"],"points":34,"win":0,"first":0},{"cards":["DQ","DA","D9","S8"],"points":28,"win":2,"first":0},{"cards":["HA","H8","D8","S7"],"points":11,"win":0,"first":2},{"cards":["D7","C7","D6","C8"],"points":0,"win":0,"first":0},{"cards":["SJ","SA","S9","SK"],"points":17,"win":3,"first":0},{"cards":["CK"],"first":3}],"player":[{"hand":[]},{"hand":[]},{"hand":["S10","H6","H7","H10"]},{"hand":[]}],"jassTyp":"SCHIEBER","gameId":0}},{"broadcast":false,"sentTo":"Computer#2","messageType":"REQUEST_CARD","data":[{"number":13,"color":"CLUBS"}]},{"broadcast":false,"receivedFrom":"Computer#2","messageType":"CHOOSE_CARD","data":{"number":6,"color":"HEARTS"}},{"broadcast":true,"messageType":"BROADCAST_GAMESTATE","data":{"version":"V0.2","trump":0,"dealer":1,"currentPlayer":1,"playerView":1,"forehand":1,"tricks":[{"cards":["DJ","DK","D10","S6"],"points":34,"win":0,"first":0},{"cards":["DQ","DA","D9","S8"],"points":28,"win":2,"first":0},{"cards":["HA","H8","D8","S7"],"points":11,"win":0,"first":2},{"cards":["D7","C7","D6","C8"],"points":0,"win":0,"first":0},{"cards":["SJ","SA","S9","SK"],"points":17,"win":3,"first":0},{"cards":["CK"],"first":3}],"player":[{"hand":[]},{"hand":["CA","HQ","SQ","HJ"]},{"hand":[]},{"hand":[]}],"jassTyp":"SCHIEBER","gameId":0}},{"broadcast":true,"messageType":"PLAYED_CARDS","data":[{"number":13,"color":"CLUBS"},{"number":6,"color":"HEARTS"}]},{"broadcast":true,"messageType":"BROADCAST_GAMESTATE","data":{"version":"V0.2","trump":0,"dealer":1,"currentPlayer":1,"playerView":1,"forehand":1,"tricks":[{"cards":["DJ","DK","D10","S6"],"points":34,"win":0,"first":0},{"cards":["DQ","DA","D9","S8"],"points":28,"win":2,"first":0},{"cards":["HA","H8","D8","S7"],"points":11,"win":0,"first":2},{"cards":["D7","C7","D6","C8"],"points":0,"win":0,"first":0},{"cards":["SJ","SA","S9","SK"],"points":17,"win":3,"first":0},{"cards":["CK","H6"],"first":3}],"player":[{"hand":[]},{"hand":["CA","HQ","SQ","HJ"]},{"hand":[]},{"hand":[]}],"jassTyp":"SCHIEBER","gameId":0}},{"broadcast":false,"sentTo":"Computer#3","messageType":"REQUEST_CARD","data":[{"number":13,"color":"CLUBS"},{"number":6,"color":"HEARTS"}]},{"broadcast":false,"receivedFrom":"Computer#3","messageType":"CHOOSE_CARD","data":{"number":14,"color":"CLUBS"}},{"broadcast":true,"messageType":"BROADCAST_GAMESTATE","data":{"version":"V0.2","trump":0,"dealer":1,"currentPlayer":0,"playerView":0,"forehand":1,"tricks":[{"cards":["DJ","DK","D10","S6"],"points":34,"win":0,"first":0},{"cards":["DQ","DA","D9","S8"],"points":28,"win":2,"first":0},{"cards":["HA","H8","D8","S7"],"points":11,"win":0,"first":2},{"cards":["D7","C7","D6","C8"],"points":0,"win":0,"first":0},{"cards":["SJ","SA","S9","SK"],"points":17,"win":3,"first":0},{"cards":["CK","H6"],"first":3}],"player":[{"hand":["HK","H9","CQ","C10"]},{"hand":[]},{"hand":[]},{"hand":[]}],"jassTyp":"SCHIEBER","gameId":0}},{"broadcast":true,"messageType":"PLAYED_CARDS","data":[{"number":13,"color":"CLUBS"},{"number":6,"color":"HEARTS"},{"number":14,"color":"CLUBS"}]},{"broadcast":true,"messageType":"BROADCAST_GAMESTATE","data":{"version":"V0.2","trump":0,"dealer":1,"currentPlayer":0,"playerView":0,"forehand":1,"tricks":[{"cards":["DJ","DK","D10","S6"],"points":34,"win":0,"first":0},{"cards":["DQ","DA","D9","S8"],"points":28,"win":2,"first":0},{"cards":["HA","H8","D8","S7"],"points":11,"win":0,"first":2},{"cards":["D7","C7","D6","C8"],"points":0,"win":0,"first":0},{"cards":["SJ","SA","S9","SK"],"points":17,"win":3,"first":0},{"cards":["CK","H6","CA"],"first":3}],"player":[{"hand":["HK","H9","CQ","C10"]},{"hand":[]},{"hand":[]},{"hand":[]}],"jassTyp":"SCHIEBER","gameId":0}},{"broadcast":false,"sentTo":"roman#0","messageType":"REQUEST_CARD","data":[{"number":13,"color":"CLUBS"},{"number":6,"color":"HEARTS"},{"number":14,"color":"CLUBS"}]},{"broadcast":false,"receivedFrom":"roman#0","messageType":"CHOOSE_CARD","data":{"number":12,"color":"CLUBS"}},{"broadcast":true,"messageType":"BROADCAST_GAMESTATE","data":{"version":"V0.2","trump":0,"dealer":1,"currentPlayer":3,"playerView":3,"forehand":1,"tricks":[{"cards":["DJ","DK","D10","S6"],"points":34,"win":0,"first":0},{"cards":["DQ","DA","D9","S8"],"points":28,"win":2,"first":0},{"cards":["HA","H8","D8","S7"],"points":11,"win":0,"first":2},{"cards":["D7","C7","D6","C8"],"points":0,"win":0,"first":0},{"cards":["SJ","SA","S9","SK"],"points":17,"win":3,"first":0},{"cards":["CK","H6","CA"],"first":3}],"player":[{"hand":[]},{"hand":[]},{"hand":[]},{"hand":["C6","C9","CJ"]}],"jassTyp":"SCHIEBER","gameId":0}},{"broadcast":true,"messageType":"PLAYED_CARDS","data":[{"number":13,"color":"CLUBS"},{"number":6,"color":"HEARTS"},{"number":14,"color":"CLUBS"},{"number":12,"color":"CLUBS"}]},{"broadcast":true,"messageType":"BROADCAST_GAMESTATE","data":{"version":"V0.2","trump":0,"dealer":1,"currentPlayer":3,"playerView":3,"forehand":1,"tricks":[{"cards":["DJ","DK","D10","S6"],"points":34,"win":0,"first":0},{"cards":["DQ","DA","D9","S8"],"points":28,"win":2,"first":0},{"cards":["HA","H8","D8","S7"],"points":11,"win":0,"first":2},{"cards":["D7","C7","D6","C8"],"points":0,"win":0,"first":0},{"cards":["SJ","SA","S9","SK"],"points":17,"win":3,"first":0},{"cards":["CK","H6","CA","CQ"],"first":3}],"player":[{"hand":[]},{"hand":[]},{"hand":[]},{"hand":["C6","C9","CJ"]}],"jassTyp":"SCHIEBER","gameId":0}},{"broadcast":true,"messageType":"BROADCAST_GAMESTATE","data":{"version":"V0.2","trump":0,"dealer":1,"currentPlayer":3,"playerView":3,"forehand":1,"tricks":[{"cards":["DJ","DK","D10","S6"],"points":34,"win":0,"first":0},{"cards":["DQ","DA","D9","S8"],"points":28,"win":2,"first":0},{"cards":["HA","H8","D8","S7"],"points":11,"win":0,"first":2},{"cards":["D7","C7","D6","C8"],"points":0,"win":0,"first":0},{"cards":["SJ","SA","S9","SK"],"points":17,"win":3,"first":0},{"cards":["CK","H6","CA","CQ"],"points":18,"first":3}],"player":[{"hand":[]},{"hand":[]},{"hand":[]},{"hand":["C6","C9","CJ"]}],"jassTyp":"SCHIEBER","gameId":0}},{"broadcast":true,"messageType":"BROADCAST_STICH","data":{"name":"Computer","id":"d5b7d243-72cc-4492-a9db-5b68e6bf62d1","seatId":3,"playedCards":[{"number":13,"color":"CLUBS"},{"number":6,"color":"HEARTS"},{"number":14,"color":"CLUBS"},{"number":12,"color":"CLUBS"}],"teams":[{"name":"Team 2","points":35,"currentRoundPoints":35,"myRound":1},{"name":"Team 1","points":73,"currentRoundPoints":73,"myRound":1}]}},{"broadcast":true,"messageType":"BROADCAST_GAMESTATE","data":{"version":"V0.2","trump":0,"dealer":1,"currentPlayer":3,"playerView":3,"forehand":1,"tricks":[{"cards":["DJ","DK","D10","S6"],"points":34,"win":0,"first":0},{"cards":["DQ","DA","D9","S8"],"points":28,"win":2,"first":0},{"cards":["HA","H8","D8","S7"],"points":11,"win":0,"first":2},{"cards":["D7","C7","D6","C8"],"points":0,"win":0,"first":0},{"cards":["SJ","SA","S9","SK"],"points":17,"win":3,"first":0},{"cards":["CK","H6","CA","CQ"],"points":18,"win":1,"first":3}],"player":[{"hand":[]},{"hand":[]},{"hand":[]},{"hand":["C6","C9","CJ"]}],"jassTyp":"SCHIEBER","gameId":0}},{"broadcast":true,"messageType":"BROADCAST_GAMESTATE","data":{"version":"V0.2","trump":0,"dealer":1,"currentPlayer":1,"playerView":1,"forehand":1,"tricks":[{"cards":["DJ","DK","D10","S6"],"points":34,"win":0,"first":0},{"cards":["DQ","DA","D9","S8"],"points":28,"win":2,"first":0},{"cards":["HA","H8","D8","S7"],"points":11,"win":0,"first":2},{"cards":["D7","C7","D6","C8"],"points":0,"win":0,"first":0},{"cards":["SJ","SA","S9","SK"],"points":17,"win":3,"first":0},{"cards":["CK","H6","CA","CQ"],"points":18,"win":1,"first":3},{"first":1}],"player":[{"hand":[]},{"hand":["HQ","SQ","HJ"]},{"hand":[]},{"hand":[]}],"jassTyp":"SCHIEBER","gameId":0}},{"broadcast":false,"sentTo":"Computer#3","messageType":"REQUEST_CARD","data":[]},{"broadcast":false,"receivedFrom":"Computer#3","messageType":"CHOOSE_CARD","data":{"number":12,"color":"SPADES"}},{"broadcast":true,"messageType":"BROADCAST_GAMESTATE","data":{"version":"V0.2","trump":0,"dealer":1,"currentPlayer":0,"playerView":0,"forehand":1,"tricks":[{"cards":["DJ","DK","D10","S6"],"points":34,"win":0,"first":0},{"cards":["DQ","DA","D9","S8"],"points":28,"win":2,"first":0},{"cards":["HA","H8","D8","S7"],"points":11,"win":0,"first":2},{"cards":["D7","C7","D6","C8"],"points":0,"win":0,"first":0},{"cards":["SJ","SA","S9","SK"],"points":17,"win":3,"first":0},{"cards":["CK","H6","CA","CQ"],"points":18,"win":1,"first":3},{"first":1}],"player":[{"hand":["HK","H9","C10"]},{"hand":[]},{"hand":[]},{"hand":[]}],"jassTyp":"SCHIEBER","gameId":0}},{"broadcast":true,"messageType":"PLAYED_CARDS","data":[{"number":12,"color":"SPADES"}]},{"broadcast":true,"messageType":"BROADCAST_GAMESTATE","data":{"version":"V0.2","trump":0,"dealer":1,"currentPlayer":0,"playerView":0,"forehand":1,"tricks":[{"cards":["DJ","DK","D10","S6"],"points":34,"win":0,"first":0},{"cards":["DQ","DA","D9","S8"],"points":28,"win":2,"first":0},{"cards":["HA","H8","D8","S7"],"points":11,"win":0,"first":2},{"cards":["D7","C7","D6","C8"],"points":0,"win":0,"first":0},{"cards":["SJ","SA","S9","SK"],"points":17,"win":3,"first":0},{"cards":["CK","H6","CA","CQ"],"points":18,"win":1,"first":3},{"cards":["SQ"],"first":1}],"player":[{"hand":["HK","H9","C10"]},{"hand":[]},{"hand":[]},{"hand":[]}],"jassTyp":"SCHIEBER","gameId":0}},{"broadcast":false,"sentTo":"roman#0","messageType":"REQUEST_CARD","data":[{"number":12,"color":"SPADES"}]},{"broadcast":false,"receivedFrom":"roman#0","messageType":"CHOOSE_CARD","data":{"number":9,"color":"HEARTS"}},{"broadcast":true,"messageType":"BROADCAST_GAMESTATE","data":{"version":"V0.2","trump":0,"dealer":1,"currentPlayer":3,"playerView":3,"forehand":1,"tricks":[{"cards":["DJ","DK","D10","S6"],"points":34,"win":0,"first":0},{"cards":["DQ","DA","D9","S8"],"points":28,"win":2,"first":0},{"cards":["HA","H8","D8","S7"],"points":11,"win":0,"first":2},{"cards":["D7","C7","D6","C8"],"points":0,"win":0,"first":0},{"cards":["SJ","SA","S9","SK"],"points":17,"win":3,"first":0},{"cards":["CK","H6","CA","CQ"],"points":18,"win":1,"first":3},{"cards":["SQ"],"first":1}],"player":[{"hand":[]},{"hand":[]},{"hand":[]},{"hand":["C6","C9","CJ"]}],"jassTyp":"SCHIEBER","gameId":0}},{"broadcast":true,"messageType":"PLAYED_CARDS","data":[{"number":12,"color":"SPADES"},{"number":9,"color":"HEARTS"}]},{"broadcast":true,"messageType":"BROADCAST_GAMESTATE","data":{"version":"V0.2","trump":0,"dealer":1,"currentPlayer":3,"playerView":3,"forehand":1,"tricks":[{"cards":["DJ","DK","D10","S6"],"points":34,"win":0,"first":0},{"cards":["DQ","DA","D9","S8"],"points":28,"win":2,"first":0},{"cards":["HA","H8","D8","S7"],"points":11,"win":0,"first":2},{"cards":["D7","C7","D6","C8"],"points":0,"win":0,"first":0},{"cards":["SJ","SA","S9","SK"],"points":17,"win":3,"first":0},{"cards":["CK","H6","CA","CQ"],"points":18,"win":1,"first":3},{"cards":["SQ","H9"],"first":1}],"player":[{"hand":[]},{"hand":[]},{"hand":[]},{"hand":["C6","C9","CJ"]}],"jassTyp":"SCHIEBER","gameId":0}},{"broadcast":false,"sentTo":"Computer#1","messageType":"REQUEST_CARD","data":[{"number":12,"color":"SPADES"},{"number":9,"color":"HEARTS"}]},{"broadcast":false,"receivedFrom":"Computer#1","messageType":"CHOOSE_CARD","data":{"number":6,"color":"CLUBS"}},{"broadcast":true,"messageType":"BROADCAST_GAMESTATE","data":{"version":"V0.2","trump":0,"dealer":1,"currentPlayer":2,"playerView":2,"forehand":1,"tricks":[{"cards":["DJ","DK","D10","S6"],"points":34,"win":0,"first":0},{"cards":["DQ","DA","D9","S8"],"points":28,"win":2,"first":0},{"cards":["HA","H8","D8","S7"],"points":11,"win":0,"first":2},{"cards":["D7","C7","D6","C8"],"points":0,"win":0,"first":0},{"cards":["SJ","SA","S9","SK"],"points":17,"win":3,"first":0},{"cards":["CK","H6","CA","CQ"],"points":18,"win":1,"first":3},{"cards":["SQ","H9"],"first":1}],"player":[{"hand":[]},{"hand":[]},{"hand":["S10","H7","H10"]},{"hand":[]}],"jassTyp":"SCHIEBER","gameId":0}},{"broadcast":true,"messageType":"PLAYED_CARDS","data":[{"number":12,"color":"SPADES"},{"number":9,"color":"HEARTS"},{"number":6,"color":"CLUBS"}]},{"broadcast":true,"messageType":"BROADCAST_GAMESTATE","data":{"version":"V0.2","trump":0,"dealer":1,"currentPlayer":2,"playerView":2,"forehand":1,"tricks":[{"cards":["DJ","DK","D10","S6"],"points":34,"win":0,"first":0},{"cards":["DQ","DA","D9","S8"],"points":28,"win":2,"first":0},{"cards":["HA","H8","D8","S7"],"points":11,"win":0,"first":2},{"cards":["D7","C7","D6","C8"],"points":0,"win":0,"first":0},{"cards":["SJ","SA","S9","SK"],"points":17,"win":3,"first":0},{"cards":["CK","H6","CA","CQ"],"points":18,"win":1,"first":3},{"cards":["SQ","H9","C6"],"first":1}],"player":[{"hand":[]},{"hand":[]},{"hand":["S10","H7","H10"]},{"hand":[]}],"jassTyp":"SCHIEBER","gameId":0}},{"broadcast":false,"sentTo":"Computer#2","messageType":"REQUEST_CARD","data":[{"number":12,"color":"SPADES"},{"number":9,"color":"HEARTS"},{"number":6,"color":"CLUBS"}]},{"broadcast":false,"receivedFrom":"Computer#2","messageType":"CHOOSE_CARD","data":{"number":10,"color":"SPADES"}},{"broadcast":true,"messageType":"BROADCAST_GAMESTATE","data":{"version":"V0.2","trump":0,"dealer":1,"currentPlayer":1,"playerView":1,"forehand":1,"tricks":[{"cards":["DJ","DK","D10","S6"],"points":34,"win":0,"first":0},{"cards":["DQ","DA","D9","S8"],"points":28,"win":2,"first":0},{"cards":["HA","H8","D8","S7"],"points":11,"win":0,"first":2},{"cards":["D7","C7","D6","C8"],"points":0,"win":0,"first":0},{"cards":["SJ","SA","S9","SK"],"points":17,"win":3,"first":0},{"cards":["CK","H6","CA","CQ"],"points":18,"win":1,"first":3},{"cards":["SQ","H9","C6"],"first":1}],"player":[{"hand":[]},{"hand":["HQ","HJ"]},{"hand":[]},{"hand":[]}],"jassTyp":"SCHIEBER","gameId":0}},{"broadcast":true,"messageType":"PLAYED_CARDS","data":[{"number":12,"color":"SPADES"},{"number":9,"color":"HEARTS"},{"number":6,"color":"CLUBS"},{"number":10,"color":"SPADES"}]},{"broadcast":true,"messageType":"BROADCAST_GAMESTATE","data":{"version":"V0.2","trump":0,"dealer":1,"currentPlayer":1,"playerView":1,"forehand":1,"tricks":[{"cards":["DJ","DK","D10","S6"],"points":34,"win":0,"first":0},{"cards":["DQ","DA","D9","S8"],"points":28,"win":2,"first":0},{"cards":["HA","H8","D8","S7"],"points":11,"win":0,"first":2},{"cards":["D7","C7","D6","C8"],"points":0,"win":0,"first":0},{"cards":["SJ","SA","S9","SK"],"points":17,"win":3,"first":0},{"cards":["CK","H6","CA","CQ"],"points":18,"win":1,"first":3},{"cards":["SQ","H9","C6","S10"],"first":1}],"player":[{"hand":[]},{"hand":["HQ","HJ"]},{"hand":[]},{"hand":[]}],"jassTyp":"SCHIEBER","gameId":0}},{"broadcast":true,"messageType":"BROADCAST_GAMESTATE","data":{"version":"V0.2","trump":0,"dealer":1,"currentPlayer":1,"playerView":1,"forehand":1,"tricks":[{"cards":["DJ","DK","D10","S6"],"points":34,"win":0,"first":0},{"cards":["DQ","DA","D9","S8"],"points":28,"win":2,"first":0},{"cards":["HA","H8","D8","S7"],"points":11,"win":0,"first":2},{"cards":["D7","C7","D6","C8"],"points":0,"win":0,"first":0},{"cards":["SJ","SA","S9","SK"],"points":17,"win":3,"first":0},{"cards":["CK","H6","CA","CQ"],"points":18,"win":1,"first":3},{"cards":["SQ","H9","C6","S10"],"points":13,"first":1}],"player":[{"hand":[]},{"hand":["HQ","HJ"]},{"hand":[]},{"hand":[]}],"jassTyp":"SCHIEBER","gameId":0}},{"broadcast":true,"messageType":"BROADCAST_STICH","data":{"name":"Computer","id":"d5b7d243-72cc-4492-a9db-5b68e6bf62d1","seatId":3,"playedCards":[{"number":12,"color":"SPADES"},{"number":9,"color":"HEARTS"},{"number":6,"color":"CLUBS"},{"number":10,"color":"SPADES"}],"teams":[{"name":"Team 2","points":48,"currentRoundPoints":48,"myRound":1},{"name":"Team 1","points":73,"currentRoundPoints":73,"myRound":1}]}},{"broadcast":true,"messageType":"BROADCAST_GAMESTATE","data":{"version":"V0.2","trump":0,"dealer":1,"currentPlayer":1,"playerView":1,"forehand":1,"tricks":[{"cards":["DJ","DK","D10","S6"],"points":34,"win":0,"first":0},{"cards":["DQ","DA","D9","S8"],"points":28,"win":2,"first":0},{"cards":["HA","H8","D8","S7"],"points":11,"win":0,"first":2},{"cards":["D7","C7","D6","C8"],"points":0,"win":0,"first":0},{"cards":["SJ","SA","S9","SK"],"points":17,"win":3,"first":0},{"cards":["CK","H6","CA","CQ"],"points":18,"win":1,"first":3},{"cards":["SQ","H9","C6","S10"],"points":13,"win":1,"first":1}],"player":[{"hand":[]},{"hand":["HQ","HJ"]},{"hand":[]},{"hand":[]}],"jassTyp":"SCHIEBER","gameId":0}},{"broadcast":true,"messageType":"BROADCAST_GAMESTATE","data":{"version":"V0.2","trump":0,"dealer":1,"currentPlayer":1,"playerView":1,"forehand":1,"tricks":[{"cards":["DJ","DK","D10","S6"],"points":34,"win":0,"first":0},{"cards":["DQ","DA","D9","S8"],"points":28,"win":2,"first":0},{"cards":["HA","H8","D8","S7"],"points":11,"win":0,"first":2},{"cards":["D7","C7","D6","C8"],"points":0,"win":0,"first":0},{"cards":["SJ","SA","S9","SK"],"points":17,"win":3,"first":0},{"cards":["CK","H6","CA","CQ"],"points":18,"win":1,"first":3},{"cards":["SQ","H9","C6","S10"],"points":13,"win":1,"first":1},{"first":1}],"player":[{"hand":[]},{"hand":["HQ","HJ"]},{"hand":[]},{"hand":[]}],"jassTyp":"SCHIEBER","gameId":0}},{"broadcast":false,"sentTo":"Computer#3","messageType":"REQUEST_CARD","data":[]},{"broadcast":false,"receivedFrom":"Computer#3","messageType":"CHOOSE_CARD","data":{"number":12,"color":"HEARTS"}},{"broadcast":true,"messageType":"BROADCAST_GAMESTATE","data":{"version":"V0.2","trump":0,"dealer":1,"currentPlayer":0,"playerView":0,"forehand":1,"tricks":[{"cards":["DJ","DK","D10","S6"],"points":34,"win":0,"first":0},{"cards":["DQ","DA","D9","S8"],"points":28,"win":2,"first":0},{"cards":["HA","H8","D8","S7"],"points":11,"win":0,"first":2},{"cards":["D7","C7","D6","C8"],"points":0,"win":0,"first":0},{"cards":["SJ","SA","S9","SK"],"points":17,"win":3,"first":0},{"cards":["CK","H6","CA","CQ"],"points":18,"win":1,"first":3},{"cards":["SQ","H9","C6","S10"],"points":13,"win":1,"first":1},{"first":1}],"player":[{"hand":["HK","C10"]},{"hand":[]},{"hand":[]},{"hand":[]}],"jassTyp":"SCHIEBER","gameId":0}},{"broadcast":true,"messageType":"PLAYED_CARDS","data":[{"number":12,"color":"HEARTS"}]},{"broadcast":true,"messageType":"BROADCAST_GAMESTATE","data":{"version":"V0.2","trump":0,"dealer":1,"currentPlayer":0,"playerView":0,"forehand":1,"tricks":[{"cards":["DJ","DK","D10","S6"],"points":34,"win":0,"first":0},{"cards":["DQ","DA","D9","S8"],"points":28,"win":2,"first":0},{"cards":["HA","H8","D8","S7"],"points":11,"win":0,"first":2},{"cards":["D7","C7","D6","C8"],"points":0,"win":0,"first":0},{"cards":["SJ","SA","S9","SK"],"points":17,"win":3,"first":0},{"cards":["CK","H6","CA","CQ"],"points":18,"win":1,"first":3},{"cards":["SQ","H9","C6","S10"],"points":13,"win":1,"first":1},{"cards":["HQ"],"first":1}],"player":[{"hand":["HK","C10"]},{"hand":[]},{"hand":[]},{"hand":[]}],"jassTyp":"SCHIEBER","gameId":0}},{"broadcast":false,"sentTo":"roman#0","messageType":"REQUEST_CARD","data":[{"number":12,"color":"HEARTS"}]},{"broadcast":false,"receivedFrom":"roman#0","messageType":"CHOOSE_CARD","data":{"number":13,"color":"HEARTS"}},{"broadcast":true,"messageType":"BROADCAST_GAMESTATE","data":{"version":"V0.2","trump":0,"dealer":1,"currentPlayer":3,"playerView":3,"forehand":1,"tricks":[{"cards":["DJ","DK","D10","S6"],"points":34,"win":0,"first":0},{"cards":["DQ","DA","D9","S8"],"points":28,"win":2,"first":0},{"cards":["HA","H8","D8","S7"],"points":11,"win":0,"first":2},{"cards":["D7","C7","D6","C8"],"points":0,"win":0,"first":0},{"cards":["SJ","SA","S9","SK"],"points":17,"win":3,"first":0},{"cards":["CK","H6","CA","CQ"],"points":18,"win":1,"first":3},{"cards":["SQ","H9","C6","S10"],"points":13,"win":1,"first":1},{"cards":["HQ"],"first":1}],"player":[{"hand":[]},{"hand":[]},{"hand":[]},{"hand":["C9","CJ"]}],"jassTyp":"SCHIEBER","gameId":0}},{"broadcast":true,"messageType":"PLAYED_CARDS","data":[{"number":12,"color":"HEARTS"},{"number":13,"color":"HEARTS"}]},{"broadcast":true,"messageType":"BROADCAST_GAMESTATE","data":{"version":"V0.2","trump":0,"dealer":1,"currentPlayer":3,"playerView":3,"forehand":1,"tricks":[{"cards":["DJ","DK","D10","S6"],"points":34,"win":0,"first":0},{"cards":["DQ","DA","D9","S8"],"points":28,"win":2,"first":0},{"cards":["HA","H8","D8","S7"],"points":11,"win":0,"first":2},{"cards":["D7","C7","D6","C8"],"points":0,"win":0,"first":0},{"cards":["SJ","SA","S9","SK"],"points":17,"win":3,"first":0},{"cards":["CK","H6","CA","CQ"],"points":18,"win":1,"first":3},{"cards":["SQ","H9","C6","S10"],"points":13,"win":1,"first":1},{"cards":["HQ","HK"],"first":1}],"player":[{"hand":[]},{"hand":[]},{"hand":[]},{"hand":["C9","CJ"]}],"jassTyp":"SCHIEBER","gameId":0}},{"broadcast":false,"sentTo":"Computer#1","messageType":"REQUEST_CARD","data":[{"number":12,"color":"HEARTS"},{"number":13,"color":"HEARTS"}]},{"broadcast":false,"receivedFrom":"Computer#1","messageType":"CHOOSE_CARD","data":{"number":9,"color":"CLUBS"}},{"broadcast":true,"messageType":"BROADCAST_GAMESTATE","data":{"version":"V0.2","trump":0,"dealer":1,"currentPlayer":2,"playerView":2,"forehand":1,"tricks":[{"cards":["DJ","DK","D10","S6"],"points":34,"win":0,"first":0},{"cards":["DQ","DA","D9","S8"],"points":28,"win":2,"first":0},{"cards":["HA","H8","D8","S7"],"points":11,"win":0,"first":2},{"cards":["D7","C7","D6","C8"],"points":0,"win":0,"first":0},{"cards":["SJ","SA","S9","SK"],"points":17,"win":3,"first":0},{"cards":["CK","H6","CA","CQ"],"points":18,"win":1,"first":3},{"cards":["SQ","H9","C6","S10"],"points":13,"win":1,"first":1},{"cards":["HQ","HK"],"first":1}],"player":[{"hand":[]},{"hand":[]},{"hand":["H7","H10"]},{"hand":[]}],"jassTyp":"SCHIEBER","gameId":0}},{"broadcast":true,"messageType":"PLAYED_CARDS","data":[{"number":12,"color":"HEARTS"},{"number":13,"color":"HEARTS"},{"number":9,"color":"CLUBS"}]},{"broadcast":true,"messageType":"BROADCAST_GAMESTATE","data":{"version":"V0.2","trump":0,"dealer":1,"currentPlayer":2,"playerView":2,"forehand":1,"tricks":[{"cards":["DJ","DK","D10","S6"],"points":34,"win":0,"first":0},{"cards":["DQ","DA","D9","S8"],"points":28,"win":2,"first":0},{"cards":["HA","H8","D8","S7"],"points":11,"win":0,"first":2},{"cards":["D7","C7","D6","C8"],"points":0,"win":0,"first":0},{"cards":["SJ","SA","S9","SK"],"points":17,"win":3,"first":0},{"cards":["CK","H6","CA","CQ"],"points":18,"win":1,"first":3},{"cards":["SQ","H9","C6","S10"],"points":13,"win":1,"first":1},{"cards":["HQ","HK","C9"],"first":1}],"player":[{"hand":[]},{"hand":[]},{"hand":["H7","H10"]},{"hand":[]}],"jassTyp":"SCHIEBER","gameId":0}},{"broadcast":false,"sentTo":"Computer#2","messageType":"REQUEST_CARD","data":[{"number":12,"color":"HEARTS"},{"number":13,"color":"HEARTS"},{"number":9,"color":"CLUBS"}]},{"broadcast":false,"receivedFrom":"Computer#2","messageType":"CHOOSE_CARD","data":{"number":10,"color":"HEARTS"}},{"broadcast":true,"messageType":"BROADCAST_GAMESTATE","data":{"version":"V0.2","trump":0,"dealer":1,"currentPlayer":1,"playerView":1,"forehand":1,"tricks":[{"cards":["DJ","DK","D10","S6"],"points":34,"win":0,"first":0},{"cards":["DQ","DA","D9","S8"],"points":28,"win":2,"first":0},{"cards":["HA","H8","D8","S7"],"points":11,"win":0,"first":2},{"cards":["D7","C7","D6","C8"],"points":0,"win":0,"first":0},{"cards":["SJ","SA","S9","SK"],"points":17,"win":3,"first":0},{"cards":["CK","H6","CA","CQ"],"points":18,"win":1,"first":3},{"cards":["SQ","H9","C6","S10"],"points":13,"win":1,"first":1},{"cards":["HQ","HK","C9"],"first":1}],"player":[{"hand":[]},{"hand":["HJ"]},{"hand":[]},{"hand":[]}],"jassTyp":"SCHIEBER","gameId":0}},{"broadcast":true,"messageType":"PLAYED_CARDS","data":[{"number":12,"color":"HEARTS"},{"number":13,"color":"HEARTS"},{"number":9,"color":"CLUBS"},{"number":10,"color":"HEARTS"}]},{"broadcast":true,"messageType":"BROADCAST_GAMESTATE","data":{"version":"V0.2","trump":0,"dealer":1,"currentPlayer":1,"playerView":1,"forehand":1,"tricks":[{"cards":["DJ","DK","D10","S6"],"points":34,"win":0,"first":0},{"cards":["DQ","DA","D9","S8"],"points":28,"win":2,"first":0},{"cards":["HA","H8","D8","S7"],"points":11,"win":0,"first":2},{"cards":["D7","C7","D6","C8"],"points":0,"win":0,"first":0},{"cards":["SJ","SA","S9","SK"],"points":17,"win":3,"first":0},{"cards":["CK","H6","CA","CQ"],"points":18,"win":1,"first":3},{"cards":["SQ","H9","C6","S10"],"points":13,"win":1,"first":1},{"cards":["HQ","HK","C9","H10"],"first":1}],"player":[{"hand":[]},{"hand":["HJ"]},{"hand":[]},{"hand":[]}],"jassTyp":"SCHIEBER","gameId":0}},{"broadcast":true,"messageType":"BROADCAST_GAMESTATE","data":{"version":"V0.2","trump":0,"dealer":1,"currentPlayer":1,"playerView":1,"forehand":1,"tricks":[{"cards":["DJ","DK","D10","S6"],"points":34,"win":0,"first":0},{"cards":["DQ","DA","D9","S8"],"points":28,"win":2,"first":0},{"cards":["HA","H8","D8","S7"],"points":11,"win":0,"first":2},{"cards":["D7","C7","D6","C8"],"points":0,"win":0,"first":0},{"cards":["SJ","SA","S9","SK"],"points":17,"win":3,"first":0},{"cards":["CK","H6","CA","CQ"],"points":18,"win":1,"first":3},{"cards":["SQ","H9","C6","S10"],"points":13,"win":1,"first":1},{"cards":["HQ","HK","C9","H10"],"points":17,"first":1}],"player":[{"hand":[]},{"hand":["HJ"]},{"hand":[]},{"hand":[]}],"jassTyp":"SCHIEBER","gameId":0}},{"broadcast":true,"messageType":"BROADCAST_STICH","data":{"name":"roman","id":"5f81f8c3-d456-4ce6-a094-1bf83f8909b8","seatId":0,"playedCards":[{"number":12,"color":"HEARTS"},{"number":13,"color":"HEARTS"},{"number":9,"color":"CLUBS"},{"number":10,"color":"HEARTS"}],"teams":[{"name":"Team 1","points":90,"currentRoundPoints":90,"myRound":1},{"name":"Team 2","points":48,"currentRoundPoints":48,"myRound":1}]}},{"broadcast":true,"messageType":"BROADCAST_GAMESTATE","data":{"version":"V0.2","trump":0,"dealer":1,"currentPlayer":1,"playerView":1,"forehand":1,"tricks":[{"cards":["DJ","DK","D10","S6"],"points":34,"win":0,"first":0},{"cards":["DQ","DA","D9","S8"],"points":28,"win":2,"first":0},{"cards":["HA","H8","D8","S7"],"points":11,"win":0,"first":2},{"cards":["D7","C7","D6","C8"],"points":0,"win":0,"first":0},{"cards":["SJ","SA","S9","SK"],"points":17,"win":3,"first":0},{"cards":["CK","H6","CA","CQ"],"points":18,"win":1,"first":3},{"cards":["SQ","H9","C6","S10"],"points":13,"win":1,"first":1},{"cards":["HQ","HK","C9","H10"],"points":17,"win":0,"first":1}],"player":[{"hand":[]},{"hand":["HJ"]},{"hand":[]},{"hand":[]}],"jassTyp":"SCHIEBER","gameId":0}},{"broadcast":true,"messageType":"BROADCAST_GAMESTATE","data":{"version":"V0.2","trump":0,"dealer":1,"currentPlayer":0,"playerView":0,"forehand":1,"tricks":[{"cards":["DJ","DK","D10","S6"],"points":34,"win":0,"first":0},{"cards":["DQ","DA","D9","S8"],"points":28,"win":2,"first":0},{"cards":["HA","H8","D8","S7"],"points":11,"win":0,"first":2},{"cards":["D7","C7","D6","C8"],"points":0,"win":0,"first":0},{"cards":["SJ","SA","S9","SK"],"points":17,"win":3,"first":0},{"cards":["CK","H6","CA","CQ"],"points":18,"win":1,"first":3},{"cards":["SQ","H9","C6","S10"],"points":13,"win":1,"first":1},{"cards":["HQ","HK","C9","H10"],"points":17,"win":0,"first":1},{"first":0}],"player":[{"hand":["C10"]},{"hand":[]},{"hand":[]},{"hand":[]}],"jassTyp":"SCHIEBER","gameId":0}},{"broadcast":false,"sentTo":"roman#0","messageType":"REQUEST_CARD","data":[]},{"broadcast":false,"receivedFrom":"roman#0","messageType":"CHOOSE_CARD","data":{"number":10,"color":"CLUBS"}},{"broadcast":true,"messageType":"BROADCAST_GAMESTATE","data":{"version":"V0.2","trump":0,"dealer":1,"currentPlayer":3,"playerView":3,"forehand":1,"tricks":[{"cards":["DJ","DK","D10","S6"],"points":34,"win":0,"first":0},{"cards":["DQ","DA","D9","S8"],"points":28,"win":2,"first":0},{"cards":["HA","H8","D8","S7"],"points":11,"win":0,"first":2},{"cards":["D7","C7","D6","C8"],"points":0,"win":0,"first":0},{"cards":["SJ","SA","S9","SK"],"points":17,"win":3,"first":0},{"cards":["CK","H6","CA","CQ"],"points":18,"win":1,"first":3},{"cards":["SQ","H9","C6","S10"],"points":13,"win":1,"first":1},{"cards":["HQ","HK","C9","H10"],"points":17,"win":0,"first":1},{"first":0}],"player":[{"hand":[]},{"hand":[]},{"hand":[]},{"hand":["CJ"]}],"jassTyp":"SCHIEBER","gameId":0}},{"broadcast":true,"messageType":"PLAYED_CARDS","data":[{"number":10,"color":"CLUBS"}]},{"broadcast":true,"messageType":"BROADCAST_GAMESTATE","data":{"version":"V0.2","trump":0,"dealer":1,"currentPlayer":3,"playerView":3,"forehand":1,"tricks":[{"cards":["DJ","DK","D10","S6"],"points":34,"win":0,"first":0},{"cards":["DQ","DA","D9","S8"],"points":28,"win":2,"first":0},{"cards":["HA","H8","D8","S7"],"points":11,"win":0,"first":2},{"cards":["D7","C7","D6","C8"],"points":0,"win":0,"first":0},{"cards":["SJ","SA","S9","SK"],"points":17,"win":3,"first":0},{"cards":["CK","H6","CA","CQ"],"points":18,"win":1,"first":3},{"cards":["SQ","H9","C6","S10"],"points":13,"win":1,"first":1},{"cards":["HQ","HK","C9","H10"],"points":17,"win":0,"first":1},{"cards":["C10"],"first":0}],"player":[{"hand":[]},{"hand":[]},{"hand":[]},{"hand":["CJ"]}],"jassTyp":"SCHIEBER","gameId":0}},{"broadcast":false,"sentTo":"Computer#1","messageType":"REQUEST_CARD","data":[{"number":10,"color":"CLUBS"}]},{"broadcast":false,"receivedFrom":"Computer#1","messageType":"CHOOSE_CARD","data":{"number":11,"color":"CLUBS"}},{"broadcast":true,"messageType":"BROADCAST_GAMESTATE","data":{"version":"V0.2","trump":0,"dealer":1,"currentPlayer":2,"playerView":2,"forehand":1,"tricks":[{"cards":["DJ","DK","D10","S6"],"points":34,"win":0,"first":0},{"cards":["DQ","DA","D9","S8"],"points":28,"win":2,"first":0},{"cards":["HA","H8","D8","S7"],"points":11,"win":0,"first":2},{"cards":["D7","C7","D6","C8"],"points":0,"win":0,"first":0},{"cards":["SJ","SA","S9","SK"],"points":17,"win":3,"first":0},{"cards":["CK","H6","CA","CQ"],"points":18,"win":1,"first":3},{"cards":["SQ","H9","C6","S10"],"points":13,"win":1,"first":1},{"cards":["HQ","HK","C9","H10"],"points":17,"win":0,"first":1},{"cards":["C10"],"first":0}],"player":[{"hand":[]},{"hand":[]},{"hand":["H7"]},{"hand":[]}],"jassTyp":"SCHIEBER","gameId":0}},{"broadcast":true,"messageType":"PLAYED_CARDS","data":[{"number":10,"color":"CLUBS"},{"number":11,"color":"CLUBS"}]},{"broadcast":true,"messageType":"BROADCAST_GAMESTATE","data":{"version":"V0.2","trump":0,"dealer":1,"currentPlayer":2,"playerView":2,"forehand":1,"tricks":[{"cards":["DJ","DK","D10","S6"],"points":34,"win":0,"first":0},{"cards":["DQ","DA","D9","S8"],"points":28,"win":2,"first":0},{"cards":["HA","H8","D8","S7"],"points":11,"win":0,"first":2},{"cards":["D7","C7","D6","C8"],"points":0,"win":0,"first":0},{"cards":["SJ","SA","S9","SK"],"points":17,"win":3,"first":0},{"cards":["CK","H6","CA","CQ"],"points":18,"win":1,"first":3},{"cards":["SQ","H9","C6","S10"],"points":13,"win":1,"first":1},{"cards":["HQ","HK","C9","H10"],"points":17,"win":0,"first":1},{"cards":["C10","CJ"],"first":0}],"player":[{"hand":[]},{"hand":[]},{"hand":["H7"]},{"hand":[]}],"jassTyp":"SCHIEBER","gameId":0}},{"broadcast":false,"sentTo":"Computer#2","messageType":"REQUEST_CARD","data":[{"number":10,"color":"CLUBS"},{"number":11,"color":"CLUBS"}]},{"broadcast":false,"receivedFrom":"Computer#2","messageType":"CHOOSE_CARD","data":{"number":7,"color":"HEARTS"}},{"broadcast":true,"messageType":"BROADCAST_GAMESTATE","data":{"version":"V0.2","trump":0,"dealer":1,"currentPlayer":1,"playerView":1,"forehand":1,"tricks":[{"cards":["DJ","DK","D10","S6"],"points":34,"win":0,"first":0},{"cards":["DQ","DA","D9","S8"],"points":28,"win":2,"first":0},{"cards":["HA","H8","D8","S7"],"points":11,"win":0,"first":2},{"cards":["D7","C7","D6","C8"],"points":0,"win":0,"first":0},{"cards":["SJ","SA","S9","SK"],"points":17,"win":3,"first":0},{"cards":["CK","H6","CA","CQ"],"points":18,"win":1,"first":3},{"cards":["SQ","H9","C6","S10"],"points":13,"win":1,"first":1},{"cards":["HQ","HK","C9","H10"],"points":17,"win":0,"first":1},{"cards":["C10","CJ"],"first":0}],"player":[{"hand":[]},{"hand":["HJ"]},{"hand":[]},{"hand":[]}],"jassTyp":"SCHIEBER","gameId":0}},{"broadcast":true,"messageType":"PLAYED_CARDS","data":[{"number":10,"color":"CLUBS"},{"number":11,"color":"CLUBS"},{"number":7,"color":"HEARTS"}]},{"broadcast":true,"messageType":"BROADCAST_GAMESTATE","data":{"version":"V0.2","trump":0,"dealer":1,"currentPlayer":1,"playerView":1,"forehand":1,"tricks":[{"cards":["DJ","DK","D10","S6"],"points":34,"win":0,"first":0},{"cards":["DQ","DA","D9","S8"],"points":28,"win":2,"first":0},{"cards":["HA","H8","D8","S7"],"points":11,"win":0,"first":2},{"cards":["D7","C7","D6","C8"],"points":0,"win":0,"first":0},{"cards":["SJ","SA","S9","SK"],"points":17,"win":3,"first":0},{"cards":["CK","H6","CA","CQ"],"points":18,"win":1,"first":3},{"cards":["SQ","H9","C6","S10"],"points":13,"win":1,"first":1},{"cards":["HQ","HK","C9","H10"],"points":17,"win":0,"first":1},{"cards":["C10","CJ","H7"],"first":0}],"player":[{"hand":[]},{"hand":["HJ"]},{"hand":[]},{"hand":[]}],"jassTyp":"SCHIEBER","gameId":0}},{"broadcast":false,"sentTo":"Computer#3","messageType":"REQUEST_CARD","data":[{"number":10,"color":"CLUBS"},{"number":11,"color":"CLUBS"},{"number":7,"color":"HEARTS"}]},{"broadcast":false,"receivedFrom":"Computer#3","messageType":"CHOOSE_CARD","data":{"number":11,"color":"HEARTS"}},{"broadcast":true,"messageType":"BROADCAST_GAMESTATE","data":{"version":"V0.2","trump":0,"dealer":1,"currentPlayer":0,"playerView":0,"forehand":1,"tricks":[{"cards":["DJ","DK","D10","S6"],"points":34,"win":0,"first":0},{"cards":["DQ","DA","D9","S8"],"points":28,"win":2,"first":0},{"cards":["HA","H8","D8","S7"],"points":11,"win":0,"first":2},{"cards":["D7","C7","D6","C8"],"points":0,"win":0,"first":0},{"cards":["SJ","SA","S9","SK"],"points":17,"win":3,"first":0},{"cards":["CK","H6","CA","CQ"],"points":18,"win":1,"first":3},{"cards":["SQ","H9","C6","S10"],"points":13,"win":1,"first":1},{"cards":["HQ","HK","C9","H10"],"points":17,"win":0,"first":1},{"cards":["C10","CJ","H7"],"first":0}],"player":[{"hand":[]},{"hand":[]},{"hand":[]},{"hand":[]}],"jassTyp":"SCHIEBER","gameId":0}},{"broadcast":true,"messageType":"PLAYED_CARDS","data":[{"number":10,"color":"CLUBS"},{"number":11,"color":"CLUBS"},{"number":7,"color":"HEARTS"},{"number":11,"color":"HEARTS"}]},{"broadcast":true,"messageType":"BROADCAST_GAMESTATE","data":{"version":"V0.2","trump":0,"dealer":1,"currentPlayer":0,"playerView":0,"forehand":1,"tricks":[{"cards":["DJ","DK","D10","S6"],"points":34,"win":0,"first":0},{"cards":["DQ","DA","D9","S8"],"points":28,"win":2,"first":0},{"cards":["HA","H8","D8","S7"],"points":11,"win":0,"first":2},{"cards":["D7","C7","D6","C8"],"points":0,"win":0,"first":0},{"cards":["SJ","SA","S9","SK"],"points":17,"win":3,"first":0},{"cards":["CK","H6","CA","CQ"],"points":18,"win":1,"first":3},{"cards":["SQ","H9","C6","S10"],"points":13,"win":1,"first":1},{"cards":["HQ","HK","C9","H10"],"points":17,"win":0,"first":1},{"cards":["C10","CJ","H7","HJ"],"first":0}],"player":[{"hand":[]},{"hand":[]},{"hand":[]},{"hand":[]}],"jassTyp":"SCHIEBER","gameId":0}},{"broadcast":true,"messageType":"BROADCAST_GAMESTATE","data":{"version":"V0.2","trump":0,"dealer":1,"currentPlayer":0,"playerView":0,"forehand":1,"tricks":[{"cards":["DJ","DK","D10","S6"],"points":34,"win":0,"first":0},{"cards":["DQ","DA","D9","S8"],"points":28,"win":2,"first":0},{"cards":["HA","H8","D8","S7"],"points":11,"win":0,"first":2},{"cards":["D7","C7","D6","C8"],"points":0,"win":0,"first":0},{"cards":["SJ","SA","S9","SK"],"points":17,"win":3,"first":0},{"cards":["CK","H6","CA","CQ"],"points":18,"win":1,"first":3},{"cards":["SQ","H9","C6","S10"],"points":13,"win":1,"first":1},{"cards":["HQ","HK","C9","H10"],"points":17,"win":0,"first":1},{"cards":["C10","CJ","H7","HJ"],"points":14,"first":0}],"player":[{"hand":[]},{"hand":[]},{"hand":[]},{"hand":[]}],"jassTyp":"SCHIEBER","gameId":0}},{"broadcast":true,"messageType":"BROADCAST_STICH","data":{"name":"Computer","id":"6f661d6d-a8fd-48b2-b9df-8b73278fafcc","seatId":1,"playedCards":[{"number":10,"color":"CLUBS"},{"number":11,"color":"CLUBS"},{"number":7,"color":"HEARTS"},{"number":11,"color":"HEARTS"}],"teams":[{"name":"Team 2","points":67,"currentRoundPoints":67,"myRound":1},{"name":"Team 1","points":90,"currentRoundPoints":90,"myRound":1}]}},{"broadcast":true,"messageType":"BROADCAST_GAME_FINISHED","data":[{"name":"Team 2","points":67,"currentRoundPoints":67,"myRound":1},{"name":"Team 1","points":90,"currentRoundPoints":90,"myRound":1}]},{"broadcast":true,"messageType":"BROADCAST_GAMESTATE","data":{"version":"V0.2","trump":0,"dealer":1,"currentPlayer":0,"playerView":0,"forehand":1,"tricks":[{"cards":["DJ","DK","D10","S6"],"points":34,"win":0,"first":0},{"cards":["DQ","DA","D9","S8"],"points":28,"win":2,"first":0},{"cards":["HA","H8","D8","S7"],"points":11,"win":0,"first":2},{"cards":["D7","C7","D6","C8"],"points":0,"win":0,"first":0},{"cards":["SJ","SA","S9","SK"],"points":17,"win":3,"first":0},{"cards":["CK","H6","CA","CQ"],"points":18,"win":1,"first":3},{"cards":["SQ","H9","C6","S10"],"points":13,"win":1,"first":1},{"cards":["HQ","HK","C9","H10"],"points":17,"win":0,"first":1},{"cards":["C10","CJ","H7","HJ"],"points":14,"win":3,"first":0}],"player":[{"hand":[]},{"hand":[]},{"hand":[]},{"hand":[]}],"jassTyp":"SCHIEBER","gameId":0}},{"broadcast":true,"messageType":"BROADCAST_GAMESTATE","data":{"version":"V0.2","trump":-1,"dealer":1,"currentPlayer":0,"playerView":0,"forehand":-1,"tricks":[],"player":[{"hand":[]},{"hand":[]},{"hand":[]},{"hand":[]}],"jassTyp":"SCHIEBER","gameId":0}},{"broadcast":true,"messageType":"BROADCAST_GAMESTATE","data":{"version":"V0.2","trump":-1,"dealer":0,"currentPlayer":3,"playerView":3,"forehand":-1,"tricks":[],"player":[{"hand":[]},{"hand":[]},{"hand":[]},{"hand":[]}],"jassTyp":"SCHIEBER","gameId":0}},{"broadcast":false,"sentTo":"roman#0","messageType":"DEAL_CARDS","data":[]},{"broadcast":false,"sentTo":"Computer#1","messageType":"DEAL_CARDS","data":[]},{"broadcast":false,"sentTo":"Computer#2","messageType":"DEAL_CARDS","data":[]},{"broadcast":false,"sentTo":"Computer#3","messageType":"DEAL_CARDS","data":[]},{"broadcast":true,"messageType":"BROADCAST_GAMESTATE","data":{"version":"V0.2","trump":-1,"dealer":0,"currentPlayer":3,"playerView":3,"forehand":-1,"tricks":[],"player":[{"hand":[]},{"hand":[]},{"hand":[]},{"hand":[]}],"jassTyp":"SCHIEBER","gameId":0}},{"broadcast":false,"sentTo":"Computer#1","messageType":"REQUEST_TRUMPF","data":false},{"broadcast":false,"receivedFrom":"Computer#1","messageType":"CHOOSE_TRUMPF","data":{"mode":"SCHIEBE","trumpfColor":"SPADES"}},{"broadcast":true,"messageType":"BROADCAST_TRUMPF","data":{"mode":"SCHIEBE","trumpfColor":"SPADES"}},{"broadcast":true,"messageType":"BROADCAST_GAMESTATE","data":{"version":"V0.2","trump":-1,"dealer":0,"currentPlayer":1,"playerView":1,"forehand":-1,"tricks":[],"player":[{"hand":[]},{"hand":[]},{"hand":[]},{"hand":[]}],"jassTyp":"SCHIEBER","gameId":0}},{"broadcast":false,"sentTo":"Computer#3","messageType":"REQUEST_TRUMPF","data":true},{"broadcast":false,"receivedFrom":"Computer#3","messageType":"CHOOSE_TRUMPF","data":{"mode":"SCHIEBE","trumpfColor":"SPADES"}},{"broadcast":true,"messageType":"BROADCAST_GAMESTATE","data":{"version":"V0.2","trump":-1,"dealer":0,"currentPlayer":1,"playerView":1,"forehand":0,"tricks":[],"player":[{"hand":[]},{"hand":[]},{"hand":[]},{"hand":[]}],"jassTyp":"SCHIEBER","gameId":0}},{"broadcast":false,"sentTo":"Computer#3","messageType":"REJECT_TRUMPF","data":{"mode":"SCHIEBE","trumpfColor":"SPADES"}},{"broadcast":false,"sentTo":"Computer#3","messageType":"REQUEST_TRUMPF","data":true},{"broadcast":false,"receivedFrom":"Computer#3","messageType":"CHOOSE_TRUMPF","data":{"mode":"TRUMPF","trumpfColor":"HEARTS"}},{"broadcast":true,"messageType":"BROADCAST_GAMESTATE","data":{"version":"V0.2","trump":-1,"dealer":0,"currentPlayer":1,"playerView":1,"forehand":0,"tricks":[],"player":[{"hand":[]},{"hand":[]},{"hand":[]},{"hand":[]}],"jassTyp":"SCHIEBER","gameId":0}},{"broadcast":true,"messageType":"BROADCAST_TRUMPF","data":{"mode":"TRUMPF","trumpfColor":"HEARTS"}},{"broadcast":true,"messageType":"BROADCAST_GAMESTATE","data":{"version":"V0.2","trump":1,"dealer":0,"currentPlayer":1,"playerView":1,"forehand":0,"tricks":[],"player":[{"hand":[]},{"hand":[]},{"hand":[]},{"hand":[]}],"jassTyp":"SCHIEBER","gameId":0}},{"broadcast":true,"messageType":"BROADCAST_GAMESTATE","data":{"version":"V0.2","trump":1,"dealer":0,"currentPlayer":3,"playerView":3,"forehand":0,"tricks":[{"first":3}],"player":[{"hand":[]},{"hand":[]},{"hand":[]},{"hand":[]}],"jassTyp":"SCHIEBER","gameId":0}},{"broadcast":false,"sentTo":"Computer#1","messageType":"REQUEST_CARD","data":[]}